[
  {
    "id": "Microsoft.Azure.WebJobs.ProjectTemplates",
    "version": "4.0.2408",
    "totalDownloads": 9141387
  },
  {
    "id": "Microsoft.Azure.WebJobs.ItemTemplates",
    "version": "4.0.2408",
    "totalDownloads": 9080918
  },
  {
    "id": "Microsoft.Azure.Functions.Worker.ItemTemplates",
    "version": "4.0.2408",
    "totalDownloads": 3743811
  },
  {
    "id": "Microsoft.Azure.Functions.Worker.ProjectTemplates",
    "version": "4.0.2408",
    "totalDownloads": 3742020
  },
  {
    "id": "NUnit3.DotNetNew.Template",
    "version": "1.9.0",
    "totalDownloads": 1583603
  },
  {
    "id": "Microsoft.iOS.Templates",
    "version": "16.2.1040+sha.dc6675cef",
    "totalDownloads": 1031977
  },
  {
    "id": "Microsoft.DotNet.Common.ProjectTemplates.5.0",
    "version": "6.0.406",
    "totalDownloads": 939863
  },
  {
    "id": "Microsoft.Android.Templates",
    "version": "34.0.0-preview.2.187+sha.d4343f9",
    "totalDownloads": 920783
  },
  {
    "id": "Microsoft.MacCatalyst.Templates",
    "version": "16.2.1040+sha.dc6675cef",
    "totalDownloads": 908751
  },
  {
    "id": "Microsoft.Maui.Templates.net6",
    "version": "6.0.552+0-sha.6e98ae942-azdo.7212333",
    "totalDownloads": 677452
  },
  {
    "id": "Microsoft.DotNet.Web.ItemTemplates",
    "version": "6.0.0-preview.7.21378.6",
    "totalDownloads": 656029
  },
  {
    "id": "Uno.ProjectTemplates.Dotnet",
    "version": "4.8.0-dev.792",
    "totalDownloads": 634827
  },
  {
    "id": "Microsoft.macOS.Templates",
    "version": "13.1.1040+sha.dc6675cef",
    "totalDownloads": 536459
  },
  {
    "id": "Take.Blip.Client.Templates",
    "version": "0.6.94-beta",
    "totalDownloads": 477389
  },
  {
    "id": "Microsoft.DotNet.Web.ProjectTemplates.5.0",
    "version": "5.0.17",
    "totalDownloads": 475796
  },
  {
    "id": "Microsoft.Maui.Templates.net7",
    "version": "7.0.59+0-sha.bf74b0ff0-azdo.7214240",
    "totalDownloads": 429993
  },
  {
    "id": "Amazon.Lambda.Templates",
    "version": "6.11.0",
    "totalDownloads": 328806
  },
  {
    "id": "HotChocolate.Templates.StarWars",
    "version": "14.0.0-preview.9",
    "totalDownloads": 288395
  },
  {
    "id": "HotChocolate.Templates.Server",
    "version": "14.0.0-preview.9",
    "totalDownloads": 286379
  },
  {
    "id": "Microsoft.DotNet.Web.ProjectTemplates.3.0",
    "version": "3.0.3",
    "totalDownloads": 264169
  },
  {
    "id": "Microsoft.DotNet.Web.Spa.ProjectTemplates.3.0",
    "version": "3.0.3",
    "totalDownloads": 250083
  },
  {
    "id": "Microsoft.tvOS.Templates",
    "version": "16.1.1537+sha.dc6675cef",
    "totalDownloads": 238481
  },
  {
    "id": "Microsoft.DotNet.Web.ProjectTemplates.3.1",
    "version": "3.1.32",
    "totalDownloads": 202461
  },
  {
    "id": "IdentityServer4.Templates",
    "version": "4.0.1",
    "totalDownloads": 194198
  },
  {
    "id": "Furion.Template.Mvc",
    "version": "4.8.7.29",
    "totalDownloads": 190952
  },
  {
    "id": "Furion.Template.Api",
    "version": "4.8.7.29",
    "totalDownloads": 190177
  },
  {
    "id": "Furion.Template.Blazor",
    "version": "4.8.7.29",
    "totalDownloads": 185192
  },
  {
    "id": "Furion.Template.Razor",
    "version": "4.8.7.29",
    "totalDownloads": 182488
  },
  {
    "id": "Furion.Template.App",
    "version": "4.8.7.29",
    "totalDownloads": 180515
  },
  {
    "id": "Furion.Template.RazorWithWebApi",
    "version": "4.8.7.29",
    "totalDownloads": 177214
  },
  {
    "id": "Microsoft.DotNet.Web.Spa.ProjectTemplates.3.1",
    "version": "3.1.32",
    "totalDownloads": 176645
  },
  {
    "id": "Furion.Template.BlazorWithWebApi",
    "version": "4.8.7.29",
    "totalDownloads": 174010
  },
  {
    "id": "Microsoft.AspNetCore.SpaTemplates",
    "version": "2.1.0-preview1-final",
    "totalDownloads": 170354
  },
  {
    "id": "Microsoft.DotNet.Web.Spa.ProjectTemplates",
    "version": "3.0.0-preview7.19365.7",
    "totalDownloads": 157195
  },
  {
    "id": "Microsoft.Maui.Templates",
    "version": "6.0.312+12-sha.c121ea3a0-azdo.6176901",
    "totalDownloads": 152124
  },
  {
    "id": "Microsoft.DotNet.Common.ProjectTemplates.3.1",
    "version": "6.0.406",
    "totalDownloads": 151040
  },
  {
    "id": "Microsoft.DotNet.Web.ProjectTemplates.2.1",
    "version": "2.1.34",
    "totalDownloads": 148368
  },
  {
    "id": "Microsoft.Maui.Templates-6.0",
    "version": "6.0.536+0-sha.850ea564d-azdo.6665768",
    "totalDownloads": 147994
  },
  {
    "id": "ppy.osu.Framework.Templates",
    "version": "2023.327.0",
    "totalDownloads": 142691
  },
  {
    "id": "HotChocolate.Templates",
    "version": "14.0.0-tags-13-1-0-preview-3.1",
    "totalDownloads": 125372
  },
  {
    "id": "SAFE.Template",
    "version": "4.2.0",
    "totalDownloads": 124648
  },
  {
    "id": "Microsoft.DotNet.Web.ProjectTemplates.2.2",
    "version": "2.2.8",
    "totalDownloads": 114811
  },
  {
    "id": "Microsoft.DotNet.Common.ItemTemplates",
    "version": "8.0.100-preview.2.23153.6",
    "totalDownloads": 105056
  },
  {
    "id": "Microsoft.DotNet.Common.ProjectTemplates.2.0",
    "version": "6.0.406",
    "totalDownloads": 101493
  },
  {
    "id": "WebSharper.Templates",
    "version": "6.1.4.277",
    "totalDownloads": 99451
  },
  {
    "id": "paule96.DotNetTemplate.GitIgnore",
    "version": "21.287.1",
    "totalDownloads": 95034
  },
  {
    "id": "Microsoft.DotNet.Web.ProjectTemplates.2.0",
    "version": "1.0.0-beta2-20170727-301",
    "totalDownloads": 92897
  },
  {
    "id": "Microsoft.Quantum.ProjectTemplates",
    "version": "0.28.263081",
    "totalDownloads": 90145
  },
  {
    "id": "Microsoft.DotNet.Web.Client.ItemTemplates",
    "version": "8.0.0-preview.2.23153.2",
    "totalDownloads": 90001
  },
  {
    "id": "Microsoft.DotNet.Web.Spa.ProjectTemplates.2.1",
    "version": "2.1.34",
    "totalDownloads": 88575
  },
  {
    "id": "Microsoft.DotNet.Test.ProjectTemplates.2.0",
    "version": "1.0.0-beta2-20170727-301",
    "totalDownloads": 85929
  },
  {
    "id": "MonoGame.Templates.CSharp",
    "version": "3.8.1.303",
    "totalDownloads": 84933
  },
  {
    "id": "MSBuild.Sdk.SqlProj.Templates",
    "version": "2.5.0",
    "totalDownloads": 84652
  },
  {
    "id": "MiniScaffold",
    "version": "0.32.0",
    "totalDownloads": 83787
  },
  {
    "id": "Umbraco.Templates",
    "version": "11.3.0-rc",
    "totalDownloads": 82392
  },
  {
    "id": "Blazor.BFF.OpenIDConnect.Template",
    "version": "2.0.2",
    "totalDownloads": 80652
  },
  {
    "id": "cloudscribe.templates",
    "version": "6.5.0",
    "totalDownloads": 77479
  },
  {
    "id": "Aksio.Templates",
    "version": "7.4.2",
    "totalDownloads": 74949
  },
  {
    "id": "Paulovich.Caju",
    "version": "0.7.3",
    "totalDownloads": 73769
  },
  {
    "id": "Cynosura.Template",
    "version": "0.4.0-b415",
    "totalDownloads": 69515
  },
  {
    "id": "Furion.SqlSugar.Template.Api",
    "version": "4.8.7.29",
    "totalDownloads": 69384
  },
  {
    "id": "Furion.SqlSugar.Template.Mvc",
    "version": "4.8.7.29",
    "totalDownloads": 67776
  },
  {
    "id": "Avalonia.Templates",
    "version": "0.10.18.7",
    "totalDownloads": 66997
  },
  {
    "id": "Furion.SqlSugar.Template.App",
    "version": "4.8.7.29",
    "totalDownloads": 65496
  },
  {
    "id": "Furion.SqlSugar.Template.Blazor",
    "version": "4.8.7.29",
    "totalDownloads": 64702
  },
  {
    "id": "Furion.SqlSugar.Template.Razor",
    "version": "4.8.7.29",
    "totalDownloads": 64290
  },
  {
    "id": "Furion.SqlSugar.Template.RazorWithWebApi",
    "version": "4.8.7.29",
    "totalDownloads": 63743
  },
  {
    "id": "Furion.SqlSugar.Template.BlazorWithWebApi",
    "version": "4.8.7.29",
    "totalDownloads": 63627
  },
  {
    "id": "Blazor.BFF.AzureB2C.Template",
    "version": "2.0.2",
    "totalDownloads": 62625
  },
  {
    "id": "Blazor.BFF.AzureAD.Template",
    "version": "2.0.2",
    "totalDownloads": 58944
  },
  {
    "id": "Boxed.Templates",
    "version": "7.14.0+build.2103",
    "totalDownloads": 57910
  },
  {
    "id": "Clean.Architecture.Solution.Template",
    "version": "7.0.1",
    "totalDownloads": 56970
  },
  {
    "id": "Threenine.ApiProject",
    "version": "4.1.7",
    "totalDownloads": 53902
  },
  {
    "id": "MvxScaffolding.Templates",
    "version": "1.16.0",
    "totalDownloads": 53185
  },
  {
    "id": "Microsoft.DotNet.Web.Spa.ProjectTemplates.5.0",
    "version": "5.0.17",
    "totalDownloads": 51928
  },
  {
    "id": "DotVVM.Templates",
    "version": "4.1.6",
    "totalDownloads": 50608
  },
  {
    "id": "ppy.osu.Game.Templates",
    "version": "2023.326.1",
    "totalDownloads": 49760
  },
  {
    "id": "giraffe-template",
    "version": "1.3.0",
    "totalDownloads": 48139
  },
  {
    "id": "Fable.Template",
    "version": "3.9.0",
    "totalDownloads": 47480
  },
  {
    "id": "Genocs.CleanArchitectureTemplate",
    "version": "2.1.0",
    "totalDownloads": 47478
  },
  {
    "id": "MudBlazor.Templates",
    "version": "0.6.3",
    "totalDownloads": 47438
  },
  {
    "id": "XrmFramework.Templates",
    "version": "2.2.55",
    "totalDownloads": 45997
  },
  {
    "id": "fake-template",
    "version": "6.0.0",
    "totalDownloads": 45730
  },
  {
    "id": "Microsoft.DotNet.Web.ProjectTemplates.6.0",
    "version": "6.0.15",
    "totalDownloads": 44845
  },
  {
    "id": "Burcin.Templates.CSharp",
    "version": "1.2.33",
    "totalDownloads": 42807
  },
  {
    "id": "AntDesign.Templates",
    "version": "0.13.0",
    "totalDownloads": 42503
  },
  {
    "id": "Amido.Stacks.CQRS.Templates",
    "version": "6.1.217",
    "totalDownloads": 41718
  },
  {
    "id": "GtkSharp.Template.CSharp",
    "version": "3.24.24.38",
    "totalDownloads": 41267
  },
  {
    "id": "OpenMod.Templates",
    "version": "3.3.10+53205e15",
    "totalDownloads": 40309
  },
  {
    "id": "Uno.Extensions.Templates",
    "version": "2.3.0-dev.918",
    "totalDownloads": 40302
  },
  {
    "id": "Runly.Templates",
    "version": "1.0.3",
    "totalDownloads": 38276
  },
  {
    "id": "OSharpNS.Template.Mvc_Angular",
    "version": "3.1.2.326",
    "totalDownloads": 38226
  },
  {
    "id": "KubeOps.Templates",
    "version": "7.1.1",
    "totalDownloads": 37999
  },
  {
    "id": "Peachpie.Templates",
    "version": "1.0.17",
    "totalDownloads": 37890
  },
  {
    "id": "HQ.Template",
    "version": "1.0.160",
    "totalDownloads": 37716
  },
  {
    "id": "JacobsApps.CleanArchitectureProjectTemplate.CSharp",
    "version": "2.6.3",
    "totalDownloads": 37353
  },
  {
    "id": "Microsoft.Identity.Web.ProjectTemplates",
    "version": "1.26.0",
    "totalDownloads": 36538
  },
  {
    "id": "Equinox.Templates",
    "version": "6.2.0",
    "totalDownloads": 36469
  },
  {
    "id": "Idea42.NetCore.Templates",
    "version": "1.0.103",
    "totalDownloads": 36067
  },
  {
    "id": "SPARocks",
    "version": "4.3.20",
    "totalDownloads": 35575
  }
]
