[
  {
    "id": "Microsoft.Azure.WebJobs.ProjectTemplates",
    "version": "4.0.2185",
    "totalDownloads": 5922806
  },
  {
    "id": "Microsoft.Azure.WebJobs.ItemTemplates",
    "version": "4.0.2185",
    "totalDownloads": 5907084
  },
  {
    "id": "NUnit3.DotNetNew.Template",
    "version": "1.9.0",
    "totalDownloads": 1565747
  },
  {
    "id": "Microsoft.Azure.Functions.Worker.ItemTemplates",
    "version": "4.0.2185",
    "totalDownloads": 980443
  },
  {
    "id": "Microsoft.Azure.Functions.Worker.ProjectTemplates",
    "version": "4.0.2185",
    "totalDownloads": 979625
  },
  {
    "id": "Microsoft.DotNet.Web.ItemTemplates",
    "version": "6.0.0-preview.7.21378.6",
    "totalDownloads": 629871
  },
  {
    "id": "Microsoft.DotNet.Common.ProjectTemplates.5.0",
    "version": "6.0.300",
    "totalDownloads": 582544
  },
  {
    "id": "Uno.ProjectTemplates.Dotnet",
    "version": "4.4.0-dev.176",
    "totalDownloads": 372374
  },
  {
    "id": "Microsoft.DotNet.Web.ProjectTemplates.5.0",
    "version": "5.0.17",
    "totalDownloads": 354664
  },
  {
    "id": "Take.Blip.Client.Templates",
    "version": "0.6.94-beta",
    "totalDownloads": 285758
  },
  {
    "id": "Microsoft.DotNet.Web.ProjectTemplates.3.0",
    "version": "3.0.3",
    "totalDownloads": 262145
  },
  {
    "id": "Microsoft.DotNet.Web.Spa.ProjectTemplates.3.0",
    "version": "3.0.3",
    "totalDownloads": 248586
  },
  {
    "id": "Amazon.Lambda.Templates",
    "version": "6.2.0",
    "totalDownloads": 230858
  },
  {
    "id": "HotChocolate.Templates.Server",
    "version": "13.0.0-preview.19",
    "totalDownloads": 204459
  },
  {
    "id": "HotChocolate.Templates.StarWars",
    "version": "13.0.0-preview.19",
    "totalDownloads": 203706
  },
  {
    "id": "Microsoft.DotNet.Web.ProjectTemplates.3.1",
    "version": "3.1.25",
    "totalDownloads": 192069
  },
  {
    "id": "IdentityServer4.Templates",
    "version": "4.0.1",
    "totalDownloads": 173400
  },
  {
    "id": "Microsoft.DotNet.Web.Spa.ProjectTemplates.3.1",
    "version": "3.1.25",
    "totalDownloads": 170573
  },
  {
    "id": "Microsoft.AspNetCore.SpaTemplates",
    "version": "2.1.0-preview1-final",
    "totalDownloads": 163579
  },
  {
    "id": "Microsoft.DotNet.Web.Spa.ProjectTemplates",
    "version": "3.0.0-preview7.19365.7",
    "totalDownloads": 152509
  },
  {
    "id": "Microsoft.DotNet.Web.ProjectTemplates.2.1",
    "version": "2.1.34",
    "totalDownloads": 146466
  },
  {
    "id": "Microsoft.DotNet.Common.ProjectTemplates.3.1",
    "version": "6.0.300",
    "totalDownloads": 131547
  },
  {
    "id": "Microsoft.iOS.Templates",
    "version": "15.4.303+sha.ce10c913a",
    "totalDownloads": 118676
  },
  {
    "id": "Microsoft.Android.Templates",
    "version": "32.0.301+sha.4c460a8",
    "totalDownloads": 118067
  },
  {
    "id": "Microsoft.Maui.Templates",
    "version": "6.0.312+12-sha.c121ea3a0-azdo.6176901",
    "totalDownloads": 113962
  },
  {
    "id": "Microsoft.DotNet.Web.ProjectTemplates.2.2",
    "version": "2.2.8",
    "totalDownloads": 113852
  },
  {
    "id": "SAFE.Template",
    "version": "3.1.1",
    "totalDownloads": 105411
  },
  {
    "id": "Microsoft.MacCatalyst.Templates",
    "version": "15.4.303+sha.ce10c913a",
    "totalDownloads": 100948
  },
  {
    "id": "HotChocolate.Templates",
    "version": "13.0.0-preview.19",
    "totalDownloads": 94349
  },
  {
    "id": "Microsoft.DotNet.Web.ProjectTemplates.2.0",
    "version": "1.0.0-beta2-20170727-301",
    "totalDownloads": 91744
  },
  {
    "id": "Microsoft.DotNet.Common.ProjectTemplates.2.0",
    "version": "6.0.300",
    "totalDownloads": 91182
  },
  {
    "id": "Microsoft.DotNet.Web.Spa.ProjectTemplates.2.1",
    "version": "2.1.34",
    "totalDownloads": 86952
  },
  {
    "id": "Microsoft.DotNet.Test.ProjectTemplates.2.0",
    "version": "1.0.0-beta2-20170727-301",
    "totalDownloads": 84847
  },
  {
    "id": "Microsoft.macOS.Templates",
    "version": "12.3.303+sha.ce10c913a",
    "totalDownloads": 81778
  },
  {
    "id": "paule96.DotNetTemplate.GitIgnore",
    "version": "21.287.1",
    "totalDownloads": 78954
  },
  {
    "id": "WebSharper.Templates",
    "version": "5.0.0.120",
    "totalDownloads": 78605
  },
  {
    "id": "ppy.osu.Framework.Templates",
    "version": "2022.604.0",
    "totalDownloads": 73886
  },
  {
    "id": "Microsoft.DotNet.Common.ItemTemplates",
    "version": "7.0.100-preview.4.22230.1",
    "totalDownloads": 73857
  },
  {
    "id": "Furion.Template.Mvc",
    "version": "3.4.2",
    "totalDownloads": 72329
  },
  {
    "id": "Furion.Template.Api",
    "version": "3.4.2",
    "totalDownloads": 71078
  },
  {
    "id": "Microsoft.Quantum.ProjectTemplates",
    "version": "0.24.210930",
    "totalDownloads": 70307
  },
  {
    "id": "MiniScaffold",
    "version": "0.31.1",
    "totalDownloads": 69391
  },
  {
    "id": "Furion.Template.Blazor",
    "version": "3.4.2",
    "totalDownloads": 67297
  },
  {
    "id": "Furion.Template.Razor",
    "version": "3.4.2",
    "totalDownloads": 67062
  },
  {
    "id": "cloudscribe.templates",
    "version": "6.0.0",
    "totalDownloads": 64468
  },
  {
    "id": "Paulovich.Caju",
    "version": "0.7.3",
    "totalDownloads": 64144
  },
  {
    "id": "Furion.Template.App",
    "version": "3.4.2",
    "totalDownloads": 62318
  },
  {
    "id": "Furion.Template.RazorWithWebApi",
    "version": "3.4.2",
    "totalDownloads": 61657
  },
  {
    "id": "Cynosura.Template",
    "version": "0.4.0-b406",
    "totalDownloads": 60051
  },
  {
    "id": "Furion.Template.BlazorWithWebApi",
    "version": "3.4.2",
    "totalDownloads": 59888
  },
  {
    "id": "Microsoft.DotNet.Web.Client.ItemTemplates",
    "version": "7.0.0-preview.4.22251.1",
    "totalDownloads": 57690
  },
  {
    "id": "MonoGame.Templates.CSharp",
    "version": "3.8.0.1641",
    "totalDownloads": 56265
  },
  {
    "id": "Boxed.Templates",
    "version": "7.13.0+build.1848",
    "totalDownloads": 49473
  },
  {
    "id": "Microsoft.DotNet.Web.Spa.ProjectTemplates.5.0",
    "version": "5.0.17",
    "totalDownloads": 48065
  },
  {
    "id": "Microsoft.tvOS.Templates",
    "version": "15.4.303+sha.ce10c913a",
    "totalDownloads": 47181
  },
  {
    "id": "MvxScaffolding.Templates",
    "version": "1.16.0",
    "totalDownloads": 45978
  },
  {
    "id": "Genocs.CleanArchitectureTemplate",
    "version": "2.1.0",
    "totalDownloads": 43858
  },
  {
    "id": "DotVVM.Templates",
    "version": "3.0.0",
    "totalDownloads": 42327
  },
  {
    "id": "giraffe-template",
    "version": "1.3.0",
    "totalDownloads": 41859
  },
  {
    "id": "Clean.Architecture.Solution.Template",
    "version": "6.0.8",
    "totalDownloads": 40474
  },
  {
    "id": "Fable.Template",
    "version": "3.6.0",
    "totalDownloads": 38799
  },
  {
    "id": "Burcin.Templates.CSharp",
    "version": "1.2.33",
    "totalDownloads": 37078
  },
  {
    "id": "fake-template",
    "version": "5.22.0",
    "totalDownloads": 36551
  },
  {
    "id": "Blazor.BFF.AzureB2C.Template",
    "version": "1.2.0",
    "totalDownloads": 35577
  },
  {
    "id": "Blazor.BFF.AzureAD.Template",
    "version": "1.2.3",
    "totalDownloads": 34971
  },
  {
    "id": "GtkSharp.Template.CSharp",
    "version": "3.24.24.38",
    "totalDownloads": 34391
  },
  {
    "id": "OSharpNS.Template.Mvc_Angular",
    "version": "3.1.2.326",
    "totalDownloads": 33690
  },
  {
    "id": "Blazor.BFF.OpenIDConnect.Template",
    "version": "1.2.1",
    "totalDownloads": 32512
  },
  {
    "id": "JacobsApps.CleanArchitectureProjectTemplate.CSharp",
    "version": "2.6.3",
    "totalDownloads": 32364
  },
  {
    "id": "Runly.Templates",
    "version": "1.0.3",
    "totalDownloads": 31971
  },
  {
    "id": "Peachpie.Templates",
    "version": "1.0.17",
    "totalDownloads": 31830
  },
  {
    "id": "Idea42.NetCore.Templates",
    "version": "1.0.103",
    "totalDownloads": 31386
  },
  {
    "id": "SPARocks",
    "version": "4.3.20",
    "totalDownloads": 31038
  },
  {
    "id": "Skoruba.IdentityServer4.Admin.Templates",
    "version": "2.1.0",
    "totalDownloads": 29145
  },
  {
    "id": "AntDesign.Templates",
    "version": "0.10.6",
    "totalDownloads": 28834
  },
  {
    "id": "OpenMod.Templates",
    "version": "3.3.0+cde5c778",
    "totalDownloads": 28444
  },
  {
    "id": "Equinox.Templates",
    "version": "5.2.1",
    "totalDownloads": 28261
  },
  {
    "id": "Piranha.Templates",
    "version": "10.1.0",
    "totalDownloads": 27971
  },
  {
    "id": "Avalonia.Templates",
    "version": "0.10.14",
    "totalDownloads": 27264
  },
  {
    "id": "HQ.Template",
    "version": "1.0.160",
    "totalDownloads": 27248
  },
  {
    "id": "Umbraco.Templates",
    "version": "10.0.0-rc4",
    "totalDownloads": 26971
  },
  {
    "id": "TimeWarp.AspNetCore.Blazor.Templates",
    "version": "5.0.169+5.0.301",
    "totalDownloads": 26760
  },
  {
    "id": "MSBuild.Sdk.SqlProj.Templates",
    "version": "2.0.0",
    "totalDownloads": 26237
  },
  {
    "id": "ExicoShopifyApp",
    "version": "1.0.434",
    "totalDownloads": 25781
  },
  {
    "id": "IdentityServer4AspNetCoreIdentityTemplate",
    "version": "6.0.1",
    "totalDownloads": 25724
  },
  {
    "id": "Genocs.CleanArchitecture",
    "version": "0.1.0",
    "totalDownloads": 25160
  },
  {
    "id": "GCC.Build.Template",
    "version": "1.19.325.4",
    "totalDownloads": 24727
  },
  {
    "id": "Genocs.MicroserviceTemplate",
    "version": "0.1.0",
    "totalDownloads": 24569
  },
  {
    "id": "Microsoft.DotNet.Web.Spa.ProjectTemplates.2.2",
    "version": "2.2.8",
    "totalDownloads": 24483
  },
  {
    "id": "MongoWebApiStarter",
    "version": "7.6.2",
    "totalDownloads": 23539
  },
  {
    "id": "Fable.Template.Elmish.React",
    "version": "0.5.0",
    "totalDownloads": 23516
  },
  {
    "id": "Microsoft.DotNet.Web.ProjectTemplates.6.0",
    "version": "6.0.5",
    "totalDownloads": 23401
  },
  {
    "id": "Feliz.Template",
    "version": "3.16.0",
    "totalDownloads": 23018
  },
  {
    "id": "Fabulous.XamarinForms.Templates",
    "version": "2.0.1",
    "totalDownloads": 22494
  },
  {
    "id": "Microsoft.Identity.Web.ProjectTemplates",
    "version": "1.25.0",
    "totalDownloads": 22255
  },
  {
    "id": "Expload.PravdaProgramTemplate",
    "version": "0.30.4-RC1",
    "totalDownloads": 22087
  },
  {
    "id": "aspnetcore-vuejs",
    "version": "1.0.9",
    "totalDownloads": 21781
  },
  {
    "id": "Prism.Forms.QuickstartTemplates",
    "version": "1.4.0",
    "totalDownloads": 21516
  },
  {
    "id": "GtkSharp.Template.VBNet",
    "version": "3.24.24.38",
    "totalDownloads": 20912
  },
  {
    "id": "TNT.AspNetCore.Mvc.Template",
    "version": "2.8.0",
    "totalDownloads": 20217
  }
]
