[
  {
    "id": "Cake.Tool",
    "version": "6.2.0",
    "totalDownloads": 160453086
  },
  {
    "id": "GitVersion.Tool",
    "version": "6.7.0",
    "totalDownloads": 112365903
  },
  {
    "id": "dotnet-ef",
    "version": "11.0.0-preview.4.26230.115",
    "totalDownloads": 111845436
  },
  {
    "id": "dotnet-reportgenerator-globaltool",
    "version": "5.5.10",
    "totalDownloads": 103128108
  },
  {
    "id": "dotnet-sonarscanner",
    "version": "11.2.1",
    "totalDownloads": 67595521
  },
  {
    "id": "dotnet-dump",
    "version": "9.0.661903",
    "totalDownloads": 63599445
  },
  {
    "id": "Swashbuckle.AspNetCore.Cli",
    "version": "10.2.1",
    "totalDownloads": 42243095
  },
  {
    "id": "dotnet-coverage",
    "version": "18.7.0",
    "totalDownloads": 40794208
  },
  {
    "id": "dotnet-serve",
    "version": "1.10.194",
    "totalDownloads": 40549795
  },
  {
    "id": "Amazon.Lambda.Tools",
    "version": "6.0.6",
    "totalDownloads": 37103724
  },
  {
    "id": "Microsoft.dotnet-interactive",
    "version": "1.0.712001",
    "totalDownloads": 35220147
  },
  {
    "id": "JetBrains.dotCover.CommandLineTools",
    "version": "2026.2.0-eap04",
    "totalDownloads": 14410110
  },
  {
    "id": "coverlet.console",
    "version": "10.0.1",
    "totalDownloads": 18057635
  },
  {
    "id": "dotnet-trace",
    "version": "9.0.661903",
    "totalDownloads": 16554744
  },
  {
    "id": "dotnet-counters",
    "version": "9.0.661903",
    "totalDownloads": 16226929
  },
  {
    "id": "Paket",
    "version": "10.3.1",
    "totalDownloads": 15905641
  },
  {
    "id": "CSharpier",
    "version": "1.2.6",
    "totalDownloads": 15290298
  },
  {
    "id": "trx2junit",
    "version": "2.1.0",
    "totalDownloads": 14429399
  },
  {
    "id": "dotnet-gcdump",
    "version": "9.0.661903",
    "totalDownloads": 13702194
  },
  {
    "id": "wix",
    "version": "7.0.0",
    "totalDownloads": 13594333
  },
  {
    "id": "JetBrains.ReSharper.GlobalTools",
    "version": "2026.2.0-eap04",
    "totalDownloads": 13396173
  },
  {
    "id": "PowerShell",
    "version": "7.6.2",
    "totalDownloads": 12562485
  },
  {
    "id": "Refitter",
    "version": "2.0.1-preview.109",
    "totalDownloads": 12242136
  },
  {
    "id": "nbgv",
    "version": "3.10.44-alpha-g09c6831bf9",
    "totalDownloads": 11895716
  },
  {
    "id": "dotnet-format",
    "version": "5.1.250801",
    "totalDownloads": 11209106
  },
  {
    "id": "AzureSignTool",
    "version": "7.0.1",
    "totalDownloads": 11041983
  },
  {
    "id": "Husky",
    "version": "0.9.1",
    "totalDownloads": 8435658
  },
  {
    "id": "CycloneDX",
    "version": "6.2.0",
    "totalDownloads": 8085608
  },
  {
    "id": "dotnet-sos",
    "version": "9.0.661903",
    "totalDownloads": 7924693
  },
  {
    "id": "NSwag.ConsoleCore",
    "version": "14.7.1",
    "totalDownloads": 7910315
  },
  {
    "id": "Microsoft.dotnet-openapi",
    "version": "11.0.0-preview.4.26230.115",
    "totalDownloads": 7740989
  },
  {
    "id": "dd-trace",
    "version": "3.45.0",
    "totalDownloads": 7670551
  },
  {
    "id": "dotnet-script",
    "version": "2.0.1",
    "totalDownloads": 7050846
  },
  {
    "id": "Octopus.DotNet.Cli",
    "version": "9.1.7",
    "totalDownloads": 6490819
  },
  {
    "id": "dotnet-outdated-tool",
    "version": "4.8.0",
    "totalDownloads": 6428484
  },
  {
    "id": "dotnet-stryker",
    "version": "4.14.2",
    "totalDownloads": 6411063
  },
  {
    "id": "docfx",
    "version": "2.78.5",
    "totalDownloads": 5131395
  },
  {
    "id": "Microsoft.SqlPackage",
    "version": "170.4.80-preview",
    "totalDownloads": 4799072
  },
  {
    "id": "SpecFlow.Plus.LivingDoc.CLI",
    "version": "3.9.57",
    "totalDownloads": 4616878
  },
  {
    "id": "minver-cli",
    "version": "8.0.0-rc.1",
    "totalDownloads": 4115415
  },
  {
    "id": "Microsoft.OpenApi.Kiota",
    "version": "1.32.0",
    "totalDownloads": 3838830
  },
  {
    "id": "AWS.CodeArtifact.NuGet.CredentialProvider",
    "version": "1.0.2",
    "totalDownloads": 3616161
  },
  {
    "id": "p",
    "version": "3.0.4",
    "totalDownloads": 3523110
  },
  {
    "id": "Amazon.Lambda.TestTool-6.0",
    "version": "0.16.3",
    "totalDownloads": 3483671
  },
  {
    "id": "Rapicgen",
    "version": "1.39.0",
    "totalDownloads": 3436504
  },
  {
    "id": "FunFair.BuildVersion",
    "version": "6.2.19.2029-main",
    "totalDownloads": 3256489
  },
  {
    "id": "NuGet.Mcp.Server",
    "version": "1.4.3",
    "totalDownloads": 3214165
  },
  {
    "id": "dotnet-svcutil",
    "version": "8.0.0",
    "totalDownloads": 3173650
  },
  {
    "id": "dotnet-stack",
    "version": "9.0.661903",
    "totalDownloads": 3143968
  },
  {
    "id": "dotnet-symbol",
    "version": "9.0.661903",
    "totalDownloads": 3082034
  },
  {
    "id": "Nuke.GlobalTool",
    "version": "10.1.0",
    "totalDownloads": 3055936
  },
  {
    "id": "dotnet-subset",
    "version": "0.3.2",
    "totalDownloads": 3005715
  },
  {
    "id": "dotnet-affected",
    "version": "6.2.0",
    "totalDownloads": 2999061
  },
  {
    "id": "fantomas",
    "version": "8.0.0-alpha-012",
    "totalDownloads": 2912761
  },
  {
    "id": "Microsoft.Playwright.CLI",
    "version": "1.2.3",
    "totalDownloads": 2836441
  },
  {
    "id": "beetle",
    "version": "1.0.5",
    "totalDownloads": 2823445
  },
  {
    "id": "dotnet-project-licenses",
    "version": "3.0.0-alpha.9",
    "totalDownloads": 2765116
  },
  {
    "id": "OctoNotes.GitHubUpdater.Tool",
    "version": "0.0.2323",
    "totalDownloads": 2763750
  },
  {
    "id": "dotnet-t4",
    "version": "3.0.0",
    "totalDownloads": 2629589
  },
  {
    "id": "snapx",
    "version": "10.0.1-prerelease.17",
    "totalDownloads": 2516466
  },
  {
    "id": "fake-cli",
    "version": "6.1.4",
    "totalDownloads": 2411896
  },
  {
    "id": "Microsoft.Crank.Agent",
    "version": "0.2.0-alpha.25473.1",
    "totalDownloads": 2410795
  },
  {
    "id": "Microsoft.CST.DevSkim.CLI",
    "version": "1.0.70",
    "totalDownloads": 2406308
  },
  {
    "id": "StrawberryShake.Tools",
    "version": "16.1.0-p.1.12",
    "totalDownloads": 2381776
  },
  {
    "id": "Amazon.Lambda.TestTool-3.1",
    "version": "0.14.1",
    "totalDownloads": 2295532
  },
  {
    "id": "Excubo.WebCompiler",
    "version": "4.4.1",
    "totalDownloads": 2189414
  },
  {
    "id": "sign",
    "version": "0.9.1-beta.26301.2",
    "totalDownloads": 2114094
  },
  {
    "id": "AWS.Deploy.Tools",
    "version": "2.0.7",
    "totalDownloads": 2103681
  },
  {
    "id": "Credfeto.ChangeLog.Cmd",
    "version": "1.10.195.1943-coverage-credfe",
    "totalDownloads": 2037062
  },
  {
    "id": "Microsoft.OpenApi.Hidi",
    "version": "3.6.0",
    "totalDownloads": 2026868
  },
  {
    "id": "Pickles.CommandLine",
    "version": "4.0.3",
    "totalDownloads": 2010927
  },
  {
    "id": "dotnet-certificate-tool",
    "version": "2.1.0",
    "totalDownloads": 1993522
  },
  {
    "id": "SpecSync.AzureDevOps",
    "version": "5.4.0",
    "totalDownloads": 1915284
  },
  {
    "id": "Uno.Check",
    "version": "1.35.0-dev.26",
    "totalDownloads": 1861557
  },
  {
    "id": "Microsoft.Sbom.DotNetTool",
    "version": "4.1.5",
    "totalDownloads": 1857601
  },
  {
    "id": "dotnet-tools-outdated",
    "version": "0.8.0",
    "totalDownloads": 1769458
  },
  {
    "id": "dafny-reportgenerator",
    "version": "1.2.0",
    "totalDownloads": 1763718
  },
  {
    "id": "Amazon.Lambda.TestTool-8.0",
    "version": "0.18.0",
    "totalDownloads": 1717450
  },
  {
    "id": "dotnet-xdt",
    "version": "2.2.1",
    "totalDownloads": 1626386
  },
  {
    "id": "Codecov.Tool",
    "version": "1.13.0",
    "totalDownloads": 1574835
  },
  {
    "id": "FluentMigrator.DotNet.Cli",
    "version": "8.0.1",
    "totalDownloads": 1547895
  },
  {
    "id": "browserstack-sdk",
    "version": "1.37.0",
    "totalDownloads": 1532057
  },
  {
    "id": "Octopus.OctoVersion.Tool",
    "version": "1.1.25",
    "totalDownloads": 1494708
  },
  {
    "id": "Microsoft.Web.LibraryManager.Cli",
    "version": "3.0.71",
    "totalDownloads": 1485575
  },
  {
    "id": "Roslynator.DotNet.Cli",
    "version": "0.12.0",
    "totalDownloads": 1479525
  },
  {
    "id": "Microsoft.VisualStudio.SlnGen.Tool",
    "version": "12.0.32",
    "totalDownloads": 1403880
  },
  {
    "id": "JetBrains.dotTrace.GlobalTools",
    "version": "2026.2.0-eap04",
    "totalDownloads": 1395498
  },
  {
    "id": "Volo.Abp.Cli",
    "version": "10.5.0-rc.1",
    "totalDownloads": 1388612
  },
  {
    "id": "nukeeper",
    "version": "0.35.0",
    "totalDownloads": 1380164
  },
  {
    "id": "dotnet-aspnet-codegenerator",
    "version": "11.0.0-preview.1.26230.3",
    "totalDownloads": 1376552
  },
  {
    "id": "Microsoft.PowerApps.CLI.Tool",
    "version": "2.8.1",
    "totalDownloads": 1375213
  },
  {
    "id": "security-scan",
    "version": "5.6.7",
    "totalDownloads": 1364117
  },
  {
    "id": "MiniCover",
    "version": "3.10.0",
    "totalDownloads": 1323201
  },
  {
    "id": "dotnet-mgcb",
    "version": "3.8.5-preview.6",
    "totalDownloads": 1303651
  },
  {
    "id": "Verify.Tool",
    "version": "0.7.0",
    "totalDownloads": 1298253
  },
  {
    "id": "GitReleaseManager.Tool",
    "version": "0.20.0",
    "totalDownloads": 1287041
  },
  {
    "id": "dotnet-test-rerun",
    "version": "4.1.0",
    "totalDownloads": 1257779
  },
  {
    "id": "nuget-license",
    "version": "4.0.10",
    "totalDownloads": 1241086
  },
  {
    "id": "Azure.Mcp",
    "version": "3.0.0-beta.16",
    "totalDownloads": 1216151
  },
  {
    "id": "Hopex.ApplicationServer.Tool",
    "version": "62.13.0.143",
    "totalDownloads": 1211960
  }
]
