[
  {
    "id": "Newtonsoft.Json",
    "version": "13.0.4-beta1",
    "totalDownloads": 6554739311
  },
  {
    "id": "Microsoft.Extensions.DependencyInjection",
    "version": "10.0.0-preview.7.25380.108",
    "totalDownloads": 5143697458
  },
  {
    "id": "Microsoft.Extensions.Logging",
    "version": "10.0.0-preview.7.25380.108",
    "totalDownloads": 4839664029
  },
  {
    "id": "System.Text.Json",
    "version": "10.0.0-preview.7.25380.108",
    "totalDownloads": 4012112807
  },
  {
    "id": "Microsoft.Bcl.AsyncInterfaces",
    "version": "10.0.0-preview.7.25380.108",
    "totalDownloads": 2807068504
  },
  {
    "id": "Azure.Core",
    "version": "1.47.2",
    "totalDownloads": 2331629998
  },
  {
    "id": "System.Drawing.Common",
    "version": "10.0.0-preview.7.25380.108",
    "totalDownloads": 2065285075
  },
  {
    "id": "Microsoft.Win32.SystemEvents",
    "version": "10.0.0-preview.7.25380.108",
    "totalDownloads": 1914514833
  },
  {
    "id": "Serilog",
    "version": "4.3.1-dev-02373",
    "totalDownloads": 1907458056
  },
  {
    "id": "Microsoft.Identity.Client",
    "version": "4.76.0",
    "totalDownloads": 1696116137
  },
  {
    "id": "Microsoft.EntityFrameworkCore",
    "version": "10.0.0-preview.7.25380.108",
    "totalDownloads": 1607850784
  },
  {
    "id": "System.Windows.Extensions",
    "version": "10.0.0-preview.7.25380.108",
    "totalDownloads": 1606719924
  },
  {
    "id": "Microsoft.IdentityModel.Abstractions",
    "version": "8.14.0",
    "totalDownloads": 1518843196
  },
  {
    "id": "Microsoft.Extensions.Http",
    "version": "10.0.0-preview.7.25380.108",
    "totalDownloads": 1462510254
  },
  {
    "id": "System.Diagnostics.EventLog",
    "version": "10.0.0-preview.7.25380.108",
    "totalDownloads": 1293055394
  },
  {
    "id": "System.Security.Cryptography.Pkcs",
    "version": "10.0.0-preview.7.25380.108",
    "totalDownloads": 1292007404
  },
  {
    "id": "AWSSDK.Core",
    "version": "4.0.0.23",
    "totalDownloads": 1289822434
  },
  {
    "id": "Castle.Core",
    "version": "5.2.1",
    "totalDownloads": 1199428259
  },
  {
    "id": "Azure.Identity",
    "version": "1.15.0",
    "totalDownloads": 1046479373
  },
  {
    "id": "System.Threading.Channels",
    "version": "10.0.0-preview.7.25380.108",
    "totalDownloads": 1009905811
  },
  {
    "id": "Swashbuckle.AspNetCore.SwaggerGen",
    "version": "9.0.3",
    "totalDownloads": 1008444687
  },
  {
    "id": "Swashbuckle.AspNetCore.Swagger",
    "version": "9.0.3",
    "totalDownloads": 1007537717
  },
  {
    "id": "Newtonsoft.Json.Bson",
    "version": "1.0.3",
    "totalDownloads": 1005733712
  },
  {
    "id": "System.Runtime.Caching",
    "version": "10.0.0-preview.7.25380.108",
    "totalDownloads": 974802087
  },
  {
    "id": "Polly",
    "version": "8.6.2",
    "totalDownloads": 974146068
  },
  {
    "id": "Microsoft.OpenApi",
    "version": "2.0.1",
    "totalDownloads": 961303820
  },
  {
    "id": "Microsoft.Data.SqlClient",
    "version": "6.1.1",
    "totalDownloads": 952088477
  },
  {
    "id": "Microsoft.Identity.Client.Extensions.Msal",
    "version": "4.76.0",
    "totalDownloads": 951169365
  },
  {
    "id": "Microsoft.Extensions.Hosting",
    "version": "10.0.0-preview.7.25380.108",
    "totalDownloads": 914876999
  },
  {
    "id": "System.Diagnostics.PerformanceCounter",
    "version": "10.0.0-preview.7.25380.108",
    "totalDownloads": 899137386
  },
  {
    "id": "System.Formats.Asn1",
    "version": "10.0.0-preview.7.25380.108",
    "totalDownloads": 896115008
  },
  {
    "id": "System.Memory.Data",
    "version": "10.0.0-preview.7.25380.108",
    "totalDownloads": 881819524
  },
  {
    "id": "AutoMapper",
    "version": "15.0.1",
    "totalDownloads": 864333215
  },
  {
    "id": "Moq",
    "version": "4.20.72",
    "totalDownloads": 864013149
  },
  {
    "id": "Swashbuckle.AspNetCore.SwaggerUI",
    "version": "9.0.3",
    "totalDownloads": 859685521
  },
  {
    "id": "Microsoft.ApplicationInsights",
    "version": "2.23.0",
    "totalDownloads": 848546169
  },
  {
    "id": "Google.Protobuf",
    "version": "3.32.0",
    "totalDownloads": 811196076
  },
  {
    "id": "Swashbuckle.AspNetCore",
    "version": "9.0.3",
    "totalDownloads": 792914128
  },
  {
    "id": "Azure.Storage.Blobs",
    "version": "12.26.0-beta.1",
    "totalDownloads": 439762007
  },
  {
    "id": "Serilog.Sinks.File",
    "version": "7.0.0",
    "totalDownloads": 785858870
  },
  {
    "id": "System.CodeDom",
    "version": "10.0.0-preview.7.25380.108",
    "totalDownloads": 776711191
  },
  {
    "id": "Microsoft.Extensions.ApiDescription.Server",
    "version": "10.0.0-preview.7.25380.108",
    "totalDownloads": 761031102
  },
  {
    "id": "Serilog.Sinks.Console",
    "version": "6.0.1-dev-00953",
    "totalDownloads": 760964044
  },
  {
    "id": "Microsoft.Data.SqlClient.SNI.runtime",
    "version": "6.0.2",
    "totalDownloads": 723448848
  },
  {
    "id": "Serilog.Extensions.Logging",
    "version": "9.0.3-dev-02320",
    "totalDownloads": 706492374
  },
  {
    "id": "Microsoft.Extensions.Logging.EventLog",
    "version": "10.0.0-preview.7.25380.108",
    "totalDownloads": 704354028
  },
  {
    "id": "xunit",
    "version": "2.9.3",
    "totalDownloads": 696261413
  },
  {
    "id": "StackExchange.Redis",
    "version": "2.8.58",
    "totalDownloads": 688455363
  },
  {
    "id": "Microsoft.Extensions.Diagnostics.HealthChecks.Abstractions",
    "version": "10.0.0-preview.7.25380.108",
    "totalDownloads": 685270438
  },
  {
    "id": "FluentValidation",
    "version": "12.0.0",
    "totalDownloads": 677220194
  },
  {
    "id": "Grpc.Core.Api",
    "version": "2.71.0",
    "totalDownloads": 664883991
  },
  {
    "id": "Microsoft.Extensions.Diagnostics.HealthChecks",
    "version": "10.0.0-preview.7.25380.108",
    "totalDownloads": 656659910
  },
  {
    "id": "Humanizer.Core",
    "version": "3.0.0-beta.96",
    "totalDownloads": 643877617
  },
  {
    "id": "coverlet.collector",
    "version": "6.0.4",
    "totalDownloads": 640557749
  },
  {
    "id": "Serilog.Settings.Configuration",
    "version": "9.0.1-dev-02317",
    "totalDownloads": 628250466
  },
  {
    "id": "Serilog.Formatting.Compact",
    "version": "3.0.0",
    "totalDownloads": 625804374
  },
  {
    "id": "Azure.Security.KeyVault.Secrets",
    "version": "4.8.0",
    "totalDownloads": 407262465
  },
  {
    "id": "Microsoft.AspNetCore.Mvc.NewtonsoftJson",
    "version": "10.0.0-preview.7.25380.108",
    "totalDownloads": 587484443
  },
  {
    "id": "Pipelines.Sockets.Unofficial",
    "version": "2.2.8",
    "totalDownloads": 584166312
  },
  {
    "id": "runtime.win-x86.runtime.native.System.Data.SqlClient.sni",
    "version": "4.4.0",
    "totalDownloads": 571437953
  },
  {
    "id": "runtime.win-x64.runtime.native.System.Data.SqlClient.sni",
    "version": "4.4.0",
    "totalDownloads": 571414431
  },
  {
    "id": "runtime.win-arm64.runtime.native.System.Data.SqlClient.sni",
    "version": "4.4.0",
    "totalDownloads": 571242560
  },
  {
    "id": "Npgsql",
    "version": "9.0.3",
    "totalDownloads": 555823158
  },
  {
    "id": "FluentAssertions",
    "version": "8.6.0",
    "totalDownloads": 536910964
  },
  {
    "id": "Microsoft.NET.Sdk.Aspire.Manifest-8.0.100",
    "version": "8.2.2",
    "totalDownloads": 531794108
  },
  {
    "id": "Serilog.Extensions.Hosting",
    "version": "9.0.1-dev-02307",
    "totalDownloads": 530870211
  },
  {
    "id": "Serilog.AspNetCore",
    "version": "9.0.0",
    "totalDownloads": 510426385
  },
  {
    "id": "Dapper",
    "version": "2.1.66",
    "totalDownloads": 508698381
  },
  {
    "id": "Microsoft.IdentityModel.Clients.ActiveDirectory",
    "version": "5.3.0",
    "totalDownloads": 507521517
  },
  {
    "id": "NUnit",
    "version": "4.4.0",
    "totalDownloads": 499518111
  },
  {
    "id": "Microsoft.Extensions.Diagnostics.Abstractions",
    "version": "10.0.0-preview.7.25380.108",
    "totalDownloads": 498398113
  },
  {
    "id": "Azure.Storage.Common",
    "version": "12.25.0-beta.1",
    "totalDownloads": 487330828
  },
  {
    "id": "Serilog.Sinks.Debug",
    "version": "3.0.0",
    "totalDownloads": 478732648
  },
  {
    "id": "Grpc.Net.Common",
    "version": "2.71.0",
    "totalDownloads": 469426006
  },
  {
    "id": "Microsoft.NET.Workload.Mono.ToolChain.Current.Manifest-8.0.100",
    "version": "8.0.19",
    "totalDownloads": 451582659
  },
  {
    "id": "Microsoft.NET.Workload.Emscripten.Current.Manifest-8.0.100",
    "version": "8.0.19",
    "totalDownloads": 451344096
  },
  {
    "id": "Microsoft.NET.Workload.Emscripten.net7.Manifest-8.0.100",
    "version": "8.0.19",
    "totalDownloads": 451088348
  },
  {
    "id": "Microsoft.NET.Workload.Mono.ToolChain.net7.Manifest-8.0.100",
    "version": "8.0.19",
    "totalDownloads": 450742891
  },
  {
    "id": "Microsoft.NET.Workload.Emscripten.net6.Manifest-8.0.100",
    "version": "8.0.19",
    "totalDownloads": 450251170
  },
  {
    "id": "Microsoft.NET.Workload.Mono.ToolChain.net6.Manifest-8.0.100",
    "version": "8.0.19",
    "totalDownloads": 449841377
  },
  {
    "id": "Grpc.Net.Client",
    "version": "2.71.0",
    "totalDownloads": 446676828
  },
  {
    "id": "Microsoft.Azure.Amqp",
    "version": "2.7.0",
    "totalDownloads": 442036727
  },
  {
    "id": "NLog",
    "version": "6.0.3",
    "totalDownloads": 441925916
  },
  {
    "id": "Microsoft.Azure.WebJobs",
    "version": "3.0.41",
    "totalDownloads": 439111637
  },
  {
    "id": "RestSharp",
    "version": "112.1.1-alpha.0.4",
    "totalDownloads": 427524871
  },
  {
    "id": "Microsoft.NET.Sdk.iOS.Manifest-8.0.100",
    "version": "18.0.8319",
    "totalDownloads": 426142372
  },
  {
    "id": "Microsoft.NET.Sdk.Android.Manifest-8.0.100",
    "version": "34.0.154",
    "totalDownloads": 425072131
  },
  {
    "id": "Microsoft.NET.Sdk.MacCatalyst.Manifest-8.0.100",
    "version": "18.0.8319",
    "totalDownloads": 424997909
  },
  {
    "id": "Microsoft.NET.Sdk.macOS.Manifest-8.0.100",
    "version": "15.0.8319",
    "totalDownloads": 424978908
  },
  {
    "id": "Microsoft.NET.Sdk.tvOS.Manifest-8.0.100",
    "version": "18.0.8319",
    "totalDownloads": 424678701
  },
  {
    "id": "Microsoft.NET.Sdk.Maui.Manifest-8.0.100",
    "version": "8.0.100",
    "totalDownloads": 424540051
  },
  {
    "id": "Autofac",
    "version": "8.4.0",
    "totalDownloads": 410685976
  },
  {
    "id": "Portable.BouncyCastle",
    "version": "1.9.0",
    "totalDownloads": 402355590
  },
  {
    "id": "AWSSDK.S3",
    "version": "4.0.6.7",
    "totalDownloads": 401726720
  },
  {
    "id": "Azure.Messaging.ServiceBus",
    "version": "7.20.1",
    "totalDownloads": 232709468
  },
  {
    "id": "Azure.Storage.Queues",
    "version": "12.24.0-beta.1",
    "totalDownloads": 125900567
  },
  {
    "id": "NUnit3TestAdapter",
    "version": "5.1.0",
    "totalDownloads": 390177275
  },
  {
    "id": "Microsoft.Extensions.Logging.ApplicationInsights",
    "version": "2.23.0",
    "totalDownloads": 370243743
  },
  {
    "id": "Microsoft.Extensions.Http.Polly",
    "version": "10.0.0-preview.7.25380.108",
    "totalDownloads": 368237554
  },
  {
    "id": "CsvHelper",
    "version": "33.1.0",
    "totalDownloads": 362092166
  }
]
