[
  {
    "id": "Newtonsoft.Json",
    "version": "13.0.5-beta1",
    "totalDownloads": 7402546021
  },
  {
    "id": "Microsoft.Extensions.DependencyInjection",
    "version": "10.0.1",
    "totalDownloads": 6022558985
  },
  {
    "id": "Microsoft.Extensions.Logging",
    "version": "10.0.1",
    "totalDownloads": 5726706956
  },
  {
    "id": "System.Text.Json",
    "version": "10.0.1",
    "totalDownloads": 4926755578
  },
  {
    "id": "Microsoft.Bcl.AsyncInterfaces",
    "version": "10.0.1",
    "totalDownloads": 3386229240
  },
  {
    "id": "Azure.Core",
    "version": "1.50.0",
    "totalDownloads": 2899902719
  },
  {
    "id": "System.Drawing.Common",
    "version": "10.0.1",
    "totalDownloads": 2347347887
  },
  {
    "id": "Serilog",
    "version": "4.3.1-dev-02395",
    "totalDownloads": 2289660812
  },
  {
    "id": "Microsoft.Win32.SystemEvents",
    "version": "10.0.1",
    "totalDownloads": 2169942451
  },
  {
    "id": "Microsoft.Identity.Client",
    "version": "4.79.2",
    "totalDownloads": 2028126559
  },
  {
    "id": "Microsoft.IdentityModel.Abstractions",
    "version": "8.15.0",
    "totalDownloads": 1983027269
  },
  {
    "id": "Microsoft.EntityFrameworkCore",
    "version": "10.0.1",
    "totalDownloads": 1872452229
  },
  {
    "id": "System.Windows.Extensions",
    "version": "10.0.1",
    "totalDownloads": 1825867123
  },
  {
    "id": "Microsoft.Extensions.Http",
    "version": "10.0.1",
    "totalDownloads": 1799396736
  },
  {
    "id": "System.Diagnostics.EventLog",
    "version": "10.0.1",
    "totalDownloads": 1677278127
  },
  {
    "id": "System.Security.Cryptography.Pkcs",
    "version": "10.0.1",
    "totalDownloads": 1580786771
  },
  {
    "id": "AWSSDK.Core",
    "version": "4.0.3.6",
    "totalDownloads": 1517385316
  },
  {
    "id": "Castle.Core",
    "version": "5.2.1",
    "totalDownloads": 1361368841
  },
  {
    "id": "Azure.Identity",
    "version": "1.18.0-beta.2",
    "totalDownloads": 1329990502
  },
  {
    "id": "System.Threading.Channels",
    "version": "10.0.1",
    "totalDownloads": 1224549619
  },
  {
    "id": "Microsoft.Identity.Client.Extensions.Msal",
    "version": "4.79.2",
    "totalDownloads": 1196823143
  },
  {
    "id": "System.Memory.Data",
    "version": "10.0.1",
    "totalDownloads": 1184175306
  },
  {
    "id": "Swashbuckle.AspNetCore.SwaggerGen",
    "version": "10.1.0",
    "totalDownloads": 1179321779
  },
  {
    "id": "Polly",
    "version": "8.6.5",
    "totalDownloads": 1174939000
  },
  {
    "id": "Swashbuckle.AspNetCore.Swagger",
    "version": "10.1.0",
    "totalDownloads": 1173576598
  },
  {
    "id": "Microsoft.OpenApi",
    "version": "3.1.1",
    "totalDownloads": 1162221016
  },
  {
    "id": "Microsoft.Data.SqlClient",
    "version": "7.0.0-preview3.25342.7",
    "totalDownloads": 1145680693
  },
  {
    "id": "Newtonsoft.Json.Bson",
    "version": "1.0.3",
    "totalDownloads": 1140519326
  },
  {
    "id": "System.Runtime.Caching",
    "version": "10.0.1",
    "totalDownloads": 1138878974
  },
  {
    "id": "System.Formats.Asn1",
    "version": "10.0.1",
    "totalDownloads": 1137334394
  },
  {
    "id": "Microsoft.Extensions.Hosting",
    "version": "10.0.1",
    "totalDownloads": 1112119578
  },
  {
    "id": "System.Diagnostics.PerformanceCounter",
    "version": "10.0.1",
    "totalDownloads": 1022422797
  },
  {
    "id": "Swashbuckle.AspNetCore.SwaggerUI",
    "version": "10.1.0",
    "totalDownloads": 1000692664
  },
  {
    "id": "Google.Protobuf",
    "version": "3.33.2",
    "totalDownloads": 999801312
  },
  {
    "id": "Microsoft.ApplicationInsights",
    "version": "3.0.0-beta1",
    "totalDownloads": 992256287
  },
  {
    "id": "System.CodeDom",
    "version": "10.0.1",
    "totalDownloads": 984950295
  },
  {
    "id": "Moq",
    "version": "4.20.72",
    "totalDownloads": 976475662
  },
  {
    "id": "AutoMapper",
    "version": "16.0.0",
    "totalDownloads": 968567910
  },
  {
    "id": "Swashbuckle.AspNetCore",
    "version": "10.1.0",
    "totalDownloads": 928834812
  },
  {
    "id": "Serilog.Sinks.File",
    "version": "8.0.0-dev-02318",
    "totalDownloads": 919015514
  },
  {
    "id": "Azure.Storage.Blobs",
    "version": "12.27.0-beta.1",
    "totalDownloads": 539635094
  },
  {
    "id": "Serilog.Sinks.Console",
    "version": "6.1.1",
    "totalDownloads": 896502803
  },
  {
    "id": "Microsoft.Extensions.ApiDescription.Server",
    "version": "10.0.1",
    "totalDownloads": 894781790
  },
  {
    "id": "Microsoft.Data.SqlClient.SNI.runtime",
    "version": "6.0.2",
    "totalDownloads": 879264394
  },
  {
    "id": "Microsoft.Extensions.Logging.EventLog",
    "version": "10.0.1",
    "totalDownloads": 867562659
  },
  {
    "id": "Microsoft.Extensions.Diagnostics.Abstractions",
    "version": "10.0.1",
    "totalDownloads": 848941998
  },
  {
    "id": "Serilog.Extensions.Logging",
    "version": "10.0.0",
    "totalDownloads": 834380166
  },
  {
    "id": "StackExchange.Redis",
    "version": "2.10.1",
    "totalDownloads": 832105793
  },
  {
    "id": "Microsoft.Extensions.Diagnostics.HealthChecks.Abstractions",
    "version": "10.0.1",
    "totalDownloads": 830041366
  },
  {
    "id": "Grpc.Core.Api",
    "version": "2.76.0",
    "totalDownloads": 823712965
  },
  {
    "id": "Microsoft.Extensions.Diagnostics.HealthChecks",
    "version": "10.0.1",
    "totalDownloads": 803482270
  },
  {
    "id": "xunit",
    "version": "2.9.3",
    "totalDownloads": 796950221
  },
  {
    "id": "Microsoft.NET.Sdk.Aspire.Manifest-8.0.100",
    "version": "8.2.2",
    "totalDownloads": 796787983
  },
  {
    "id": "FluentValidation",
    "version": "12.1.1",
    "totalDownloads": 794969250
  },
  {
    "id": "Humanizer.Core",
    "version": "3.0.1",
    "totalDownloads": 767959756
  },
  {
    "id": "coverlet.collector",
    "version": "6.0.4",
    "totalDownloads": 754804452
  },
  {
    "id": "Serilog.Settings.Configuration",
    "version": "10.0.0",
    "totalDownloads": 737586216
  },
  {
    "id": "Serilog.Formatting.Compact",
    "version": "3.0.0",
    "totalDownloads": 732869571
  },
  {
    "id": "Azure.Security.KeyVault.Secrets",
    "version": "4.8.0",
    "totalDownloads": 494434185
  },
  {
    "id": "Pipelines.Sockets.Unofficial",
    "version": "2.2.8",
    "totalDownloads": 687244311
  },
  {
    "id": "Microsoft.AspNetCore.Mvc.NewtonsoftJson",
    "version": "10.0.1",
    "totalDownloads": 670766879
  },
  {
    "id": "Npgsql",
    "version": "10.0.1",
    "totalDownloads": 667991697
  },
  {
    "id": "runtime.win-x86.runtime.native.System.Data.SqlClient.sni",
    "version": "4.4.0",
    "totalDownloads": 635414444
  },
  {
    "id": "runtime.win-x64.runtime.native.System.Data.SqlClient.sni",
    "version": "4.4.0",
    "totalDownloads": 635373903
  },
  {
    "id": "runtime.win-arm64.runtime.native.System.Data.SqlClient.sni",
    "version": "4.4.0",
    "totalDownloads": 635172971
  },
  {
    "id": "Serilog.Extensions.Hosting",
    "version": "10.0.0",
    "totalDownloads": 631797104
  },
  {
    "id": "FluentAssertions",
    "version": "8.8.0",
    "totalDownloads": 608051728
  },
  {
    "id": "Grpc.Net.Common",
    "version": "2.76.0",
    "totalDownloads": 601161438
  },
  {
    "id": "Serilog.AspNetCore",
    "version": "10.0.0",
    "totalDownloads": 600119603
  },
  {
    "id": "Microsoft.NET.Workload.Mono.ToolChain.Current.Manifest-8.0.100",
    "version": "8.0.22",
    "totalDownloads": 595754546
  },
  {
    "id": "Microsoft.NET.Workload.Emscripten.Current.Manifest-8.0.100",
    "version": "8.0.22",
    "totalDownloads": 595520477
  },
  {
    "id": "Microsoft.NET.Workload.Emscripten.net7.Manifest-8.0.100",
    "version": "8.0.22",
    "totalDownloads": 595238873
  },
  {
    "id": "Microsoft.NET.Workload.Mono.ToolChain.net7.Manifest-8.0.100",
    "version": "8.0.22",
    "totalDownloads": 594829507
  },
  {
    "id": "Microsoft.NET.Workload.Emscripten.net6.Manifest-8.0.100",
    "version": "8.0.22",
    "totalDownloads": 594395835
  },
  {
    "id": "Microsoft.NET.Workload.Mono.ToolChain.net6.Manifest-8.0.100",
    "version": "8.0.22",
    "totalDownloads": 593926723
  },
  {
    "id": "Azure.Storage.Common",
    "version": "12.26.0-beta.1",
    "totalDownloads": 592032914
  },
  {
    "id": "Dapper",
    "version": "2.1.66",
    "totalDownloads": 588235469
  },
  {
    "id": "Grpc.Net.Client",
    "version": "2.76.0",
    "totalDownloads": 578345389
  },
  {
    "id": "System.ClientModel",
    "version": "1.8.1",
    "totalDownloads": 570183710
  },
  {
    "id": "Serilog.Sinks.Debug",
    "version": "3.0.0",
    "totalDownloads": 564545484
  },
  {
    "id": "Microsoft.NET.Sdk.iOS.Manifest-8.0.100",
    "version": "18.0.8319",
    "totalDownloads": 562012191
  },
  {
    "id": "NUnit",
    "version": "4.4.0",
    "totalDownloads": 561089674
  },
  {
    "id": "Microsoft.NET.Sdk.Android.Manifest-8.0.100",
    "version": "34.0.154",
    "totalDownloads": 560948220
  },
  {
    "id": "Microsoft.NET.Sdk.MacCatalyst.Manifest-8.0.100",
    "version": "18.0.8319",
    "totalDownloads": 560853584
  },
  {
    "id": "Microsoft.NET.Sdk.macOS.Manifest-8.0.100",
    "version": "15.0.8319",
    "totalDownloads": 560831512
  },
  {
    "id": "Microsoft.NET.Sdk.tvOS.Manifest-8.0.100",
    "version": "18.0.8319",
    "totalDownloads": 560518619
  },
  {
    "id": "Microsoft.Extensions.Diagnostics",
    "version": "10.0.1",
    "totalDownloads": 560433578
  },
  {
    "id": "Microsoft.NET.Sdk.Maui.Manifest-8.0.100",
    "version": "8.0.100",
    "totalDownloads": 560313856
  },
  {
    "id": "Microsoft.IdentityModel.Clients.ActiveDirectory",
    "version": "5.3.0",
    "totalDownloads": 540890896
  },
  {
    "id": "Microsoft.Azure.Amqp",
    "version": "2.7.0",
    "totalDownloads": 522170937
  },
  {
    "id": "NLog",
    "version": "6.0.7",
    "totalDownloads": 499194859
  },
  {
    "id": "Microsoft.Azure.WebJobs",
    "version": "3.0.44",
    "totalDownloads": 493893659
  },
  {
    "id": "OpenTelemetry.Api",
    "version": "1.14.0",
    "totalDownloads": 485402280
  },
  {
    "id": "AWSSDK.S3",
    "version": "4.0.16.1",
    "totalDownloads": 482078803
  },
  {
    "id": "RestSharp",
    "version": "113.0.1-alpha.0.3",
    "totalDownloads": 481282465
  },
  {
    "id": "Azure.Messaging.ServiceBus",
    "version": "7.20.1",
    "totalDownloads": 286658267
  },
  {
    "id": "Autofac",
    "version": "9.0.0",
    "totalDownloads": 463947015
  },
  {
    "id": "NUnit3TestAdapter",
    "version": "6.0.1",
    "totalDownloads": 443033469
  },
  {
    "id": "Azure.Storage.Queues",
    "version": "12.25.0-beta.1",
    "totalDownloads": 154613829
  },
  {
    "id": "Portable.BouncyCastle",
    "version": "1.9.0",
    "totalDownloads": 442721091
  }
]
