[
  {
    "id": "Newtonsoft.Json",
    "version": "13.0.2-beta2",
    "totalDownloads": 2213565084
  },
  {
    "id": "Microsoft.Extensions.DependencyInjection",
    "version": "7.0.0-preview.7.22375.6",
    "totalDownloads": 1423243643
  },
  {
    "id": "Microsoft.Extensions.Logging",
    "version": "7.0.0-preview.7.22375.6",
    "totalDownloads": 1345848663
  },
  {
    "id": "Microsoft.Bcl.AsyncInterfaces",
    "version": "7.0.0-preview.7.22375.6",
    "totalDownloads": 525876175
  },
  {
    "id": "System.Text.Json",
    "version": "7.0.0-preview.7.22375.6",
    "totalDownloads": 524224642
  },
  {
    "id": "Serilog",
    "version": "2.12.0-dev-01559",
    "totalDownloads": 519556232
  },
  {
    "id": "Microsoft.EntityFrameworkCore",
    "version": "7.0.0-preview.7.22376.2",
    "totalDownloads": 480852868
  },
  {
    "id": "System.Drawing.Common",
    "version": "7.0.0-preview.7.22375.6",
    "totalDownloads": 450300089
  },
  {
    "id": "Castle.Core",
    "version": "5.1.0",
    "totalDownloads": 418234150
  },
  {
    "id": "Microsoft.Win32.SystemEvents",
    "version": "7.0.0-preview.7.22375.6",
    "totalDownloads": 414197188
  },
  {
    "id": "Moq",
    "version": "4.18.2",
    "totalDownloads": 326884163
  },
  {
    "id": "System.Windows.Extensions",
    "version": "7.0.0-preview.7.22375.6",
    "totalDownloads": 318547241
  },
  {
    "id": "AWSSDK.Core",
    "version": "3.7.12.29",
    "totalDownloads": 309391807
  },
  {
    "id": "Microsoft.Identity.Client",
    "version": "4.46.2",
    "totalDownloads": 304793050
  },
  {
    "id": "AutoMapper",
    "version": "11.0.1",
    "totalDownloads": 297265154
  },
  {
    "id": "Newtonsoft.Json.Bson",
    "version": "1.0.3-beta1",
    "totalDownloads": 297156806
  },
  {
    "id": "Microsoft.ApplicationInsights",
    "version": "2.21.0",
    "totalDownloads": 288421914
  },
  {
    "id": "Microsoft.Extensions.Http",
    "version": "7.0.0-preview.7.22375.6",
    "totalDownloads": 285264760
  },
  {
    "id": "Swashbuckle.AspNetCore.Swagger",
    "version": "6.4.0",
    "totalDownloads": 272334894
  },
  {
    "id": "Swashbuckle.AspNetCore.SwaggerGen",
    "version": "6.4.0",
    "totalDownloads": 270799409
  },
  {
    "id": "Azure.Core",
    "version": "1.25.0",
    "totalDownloads": 268055978
  },
  {
    "id": "System.Security.Cryptography.Pkcs",
    "version": "7.0.0-preview.7.22375.6",
    "totalDownloads": 258855708
  },
  {
    "id": "System.Diagnostics.PerformanceCounter",
    "version": "7.0.0-preview.7.22375.6",
    "totalDownloads": 257442438
  },
  {
    "id": "Microsoft.IdentityModel.Clients.ActiveDirectory",
    "version": "5.2.9",
    "totalDownloads": 248463078
  },
  {
    "id": "Swashbuckle.AspNetCore.SwaggerUI",
    "version": "6.4.0",
    "totalDownloads": 244456096
  },
  {
    "id": "Azure.Storage.Blobs",
    "version": "12.14.0-beta.1",
    "totalDownloads": 68063982
  },
  {
    "id": "xunit",
    "version": "2.4.2",
    "totalDownloads": 239215333
  },
  {
    "id": "Polly",
    "version": "7.2.3",
    "totalDownloads": 232613457
  },
  {
    "id": "Serilog.Sinks.File",
    "version": "5.0.1-dev-00947",
    "totalDownloads": 232582444
  },
  {
    "id": "Swashbuckle.AspNetCore",
    "version": "6.4.0",
    "totalDownloads": 223119270
  },
  {
    "id": "System.Runtime.Caching",
    "version": "7.0.0-preview.7.22375.6",
    "totalDownloads": 219950163
  },
  {
    "id": "Microsoft.Extensions.Hosting",
    "version": "7.0.0-preview.7.22375.6",
    "totalDownloads": 219358342
  },
  {
    "id": "Microsoft.Data.SqlClient",
    "version": "5.0.0",
    "totalDownloads": 201367281
  },
  {
    "id": "Serilog.Sinks.Console",
    "version": "4.1.0",
    "totalDownloads": 200069414
  },
  {
    "id": "System.Threading.Channels",
    "version": "7.0.0-preview.7.22375.6",
    "totalDownloads": 199218127
  },
  {
    "id": "Serilog.Extensions.Logging",
    "version": "3.1.1-dev-10301",
    "totalDownloads": 198424715
  },
  {
    "id": "NUnit",
    "version": "3.13.3",
    "totalDownloads": 195391121
  },
  {
    "id": "Microsoft.OpenApi",
    "version": "1.4.0",
    "totalDownloads": 193662265
  },
  {
    "id": "System.Diagnostics.EventLog",
    "version": "7.0.0-preview.7.22375.6",
    "totalDownloads": 180302028
  },
  {
    "id": "EntityFramework",
    "version": "6.4.4",
    "totalDownloads": 176351438
  },
  {
    "id": "runtime.win-x86.runtime.native.System.Data.SqlClient.sni",
    "version": "4.4.0",
    "totalDownloads": 175581046
  },
  {
    "id": "runtime.win-x64.runtime.native.System.Data.SqlClient.sni",
    "version": "4.4.0",
    "totalDownloads": 175546256
  },
  {
    "id": "runtime.win-arm64.runtime.native.System.Data.SqlClient.sni",
    "version": "4.4.0",
    "totalDownloads": 175489053
  },
  {
    "id": "FluentAssertions",
    "version": "6.7.0",
    "totalDownloads": 174665382
  },
  {
    "id": "Microsoft.AspNetCore.Mvc.NewtonsoftJson",
    "version": "7.0.0-preview.7.22376.6",
    "totalDownloads": 172299404
  },
  {
    "id": "StackExchange.Redis",
    "version": "2.6.66",
    "totalDownloads": 171658255
  },
  {
    "id": "FluentValidation",
    "version": "11.2.1",
    "totalDownloads": 171500559
  },
  {
    "id": "Microsoft.Extensions.ApiDescription.Server",
    "version": "7.0.0-preview.7.22376.6",
    "totalDownloads": 171407066
  },
  {
    "id": "NLog",
    "version": "5.0.4",
    "totalDownloads": 170112777
  },
  {
    "id": "Serilog.Formatting.Compact",
    "version": "1.1.1-dev-00944",
    "totalDownloads": 168797690
  },
  {
    "id": "Dapper",
    "version": "2.0.123",
    "totalDownloads": 162981652
  },
  {
    "id": "Autofac",
    "version": "6.4.0",
    "totalDownloads": 162763329
  },
  {
    "id": "Azure.Security.KeyVault.Secrets",
    "version": "4.3.0",
    "totalDownloads": 56246687
  },
  {
    "id": "Serilog.Settings.Configuration",
    "version": "3.3.1-dev-00337",
    "totalDownloads": 160164374
  },
  {
    "id": "Azure.Storage.Queues",
    "version": "12.12.0-beta.1",
    "totalDownloads": 16554531
  },
  {
    "id": "Microsoft.AspNet.Mvc",
    "version": "5.2.9",
    "totalDownloads": 151153319
  },
  {
    "id": "Microsoft.Azure.WebJobs",
    "version": "3.0.33",
    "totalDownloads": 150406560
  },
  {
    "id": "RestSharp",
    "version": "108.0.2-alpha.0.6",
    "totalDownloads": 150135215
  },
  {
    "id": "IdentityModel",
    "version": "6.1.0-preview.1",
    "totalDownloads": 149559999
  },
  {
    "id": "Google.Protobuf",
    "version": "3.21.5",
    "totalDownloads": 148002657
  },
  {
    "id": "Microsoft.Extensions.Logging.EventLog",
    "version": "7.0.0-preview.7.22375.6",
    "totalDownloads": 143971952
  },
  {
    "id": "Pipelines.Sockets.Unofficial",
    "version": "2.2.2",
    "totalDownloads": 142486730
  },
  {
    "id": "coverlet.collector",
    "version": "3.1.2",
    "totalDownloads": 140111744
  },
  {
    "id": "Microsoft.AspNetCore.Mvc",
    "version": "2.2.0",
    "totalDownloads": 139012916
  },
  {
    "id": "Npgsql",
    "version": "7.0.0-preview.7",
    "totalDownloads": 138636570
  },
  {
    "id": "Microsoft.Azure.Services.AppAuthentication",
    "version": "1.6.2",
    "totalDownloads": 138569613
  },
  {
    "id": "Serilog.AspNetCore",
    "version": "6.1.0-dev-00281",
    "totalDownloads": 136665115
  },
  {
    "id": "jQuery",
    "version": "3.6.0",
    "totalDownloads": 136498736
  },
  {
    "id": "NUnit3TestAdapter",
    "version": "4.3.0-alpha-net7.4",
    "totalDownloads": 133623908
  },
  {
    "id": "log4net",
    "version": "2.0.15",
    "totalDownloads": 132111270
  },
  {
    "id": "Microsoft.Extensions.Diagnostics.HealthChecks.Abstractions",
    "version": "7.0.0-preview.7.22376.6",
    "totalDownloads": 130580419
  },
  {
    "id": "Microsoft.Bcl.HashCode",
    "version": "1.1.1",
    "totalDownloads": 129952734
  },
  {
    "id": "Microsoft.Extensions.Diagnostics.HealthChecks",
    "version": "7.0.0-preview.7.22376.6",
    "totalDownloads": 127288063
  },
  {
    "id": "Microsoft.Azure.Amqp",
    "version": "2.5.12",
    "totalDownloads": 124318579
  },
  {
    "id": "Serilog.Extensions.Hosting",
    "version": "5.0.1",
    "totalDownloads": 124245932
  },
  {
    "id": "Azure.Security.KeyVault.Certificates",
    "version": "4.3.0",
    "totalDownloads": 18932331
  },
  {
    "id": "Portable.BouncyCastle",
    "version": "1.9.0",
    "totalDownloads": 122816744
  },
  {
    "id": "Azure.Messaging.ServiceBus",
    "version": "7.10.0",
    "totalDownloads": 21968544
  },
  {
    "id": "Microsoft.AspNet.WebApi",
    "version": "5.2.9",
    "totalDownloads": 118610418
  },
  {
    "id": "Serilog.Sinks.Debug",
    "version": "2.0.0",
    "totalDownloads": 117818949
  },
  {
    "id": "Humanizer.Core",
    "version": "2.14.1",
    "totalDownloads": 117708685
  },
  {
    "id": "Microsoft.Data.OData",
    "version": "5.8.5",
    "totalDownloads": 116957830
  },
  {
    "id": "System.CodeDom",
    "version": "7.0.0-preview.7.22375.6",
    "totalDownloads": 116803645
  },
  {
    "id": "Serilog.Sinks.PeriodicBatching",
    "version": "2.3.1",
    "totalDownloads": 115371541
  },
  {
    "id": "Azure.Security.KeyVault.Keys",
    "version": "4.3.0",
    "totalDownloads": 7199215
  },
  {
    "id": "System.Interactive.Async",
    "version": "6.0.1",
    "totalDownloads": 111319419
  },
  {
    "id": "RabbitMQ.Client",
    "version": "6.4.0",
    "totalDownloads": 110564741
  },
  {
    "id": "AutoMapper.Extensions.Microsoft.DependencyInjection",
    "version": "11.0.0",
    "totalDownloads": 110252672
  },
  {
    "id": "AWSSDK.S3",
    "version": "3.7.9.47",
    "totalDownloads": 109861494
  },
  {
    "id": "MongoDB.Bson",
    "version": "2.17.1",
    "totalDownloads": 107175413
  },
  {
    "id": "Microsoft.Data.SqlClient.SNI.runtime",
    "version": "5.0.0",
    "totalDownloads": 102838813
  },
  {
    "id": "CsvHelper",
    "version": "28.0.1",
    "totalDownloads": 102004714
  },
  {
    "id": "Microsoft.Extensions.Logging.ApplicationInsights",
    "version": "2.21.0",
    "totalDownloads": 101707712
  },
  {
    "id": "SQLitePCLRaw.core",
    "version": "2.1.1",
    "totalDownloads": 101406775
  },
  {
    "id": "Microsoft.Azure.Cosmos",
    "version": "3.30.1",
    "totalDownloads": 31214179
  },
  {
    "id": "WebGrease",
    "version": "1.6.0",
    "totalDownloads": 100158717
  },
  {
    "id": "MongoDB.Driver.Core",
    "version": "2.17.1",
    "totalDownloads": 99985770
  },
  {
    "id": "Elasticsearch.Net",
    "version": "7.17.4",
    "totalDownloads": 99462726
  },
  {
    "id": "MongoDB.Driver",
    "version": "2.17.1",
    "totalDownloads": 95948650
  },
  {
    "id": "Remotion.Linq",
    "version": "2.2.0",
    "totalDownloads": 94252688
  }
]
