[
  {
    "id": "Newtonsoft.Json",
    "version": "13.0.3",
    "totalDownloads": 2956208214
  },
  {
    "id": "Microsoft.Extensions.DependencyInjection",
    "version": "8.0.0-preview.2.23128.3",
    "totalDownloads": 1979663921
  },
  {
    "id": "Microsoft.Extensions.Logging",
    "version": "8.0.0-preview.2.23128.3",
    "totalDownloads": 1857472202
  },
  {
    "id": "System.Text.Json",
    "version": "8.0.0-preview.2.23128.3",
    "totalDownloads": 936306029
  },
  {
    "id": "Microsoft.Bcl.AsyncInterfaces",
    "version": "8.0.0-preview.2.23128.3",
    "totalDownloads": 808951101
  },
  {
    "id": "System.Drawing.Common",
    "version": "8.0.0-preview.2.23128.3",
    "totalDownloads": 705013258
  },
  {
    "id": "Serilog",
    "version": "3.0.0-dev-01926",
    "totalDownloads": 701611406
  },
  {
    "id": "Microsoft.Win32.SystemEvents",
    "version": "8.0.0-preview.2.23128.3",
    "totalDownloads": 652918527
  },
  {
    "id": "Microsoft.EntityFrameworkCore",
    "version": "8.0.0-preview.2.23128.3",
    "totalDownloads": 643059786
  },
  {
    "id": "Castle.Core",
    "version": "5.1.1",
    "totalDownloads": 539520320
  },
  {
    "id": "System.Windows.Extensions",
    "version": "8.0.0-preview.2.23128.3",
    "totalDownloads": 522750933
  },
  {
    "id": "Microsoft.Identity.Client",
    "version": "4.51.0",
    "totalDownloads": 475268635
  },
  {
    "id": "Azure.Core",
    "version": "1.30.0",
    "totalDownloads": 468482379
  },
  {
    "id": "AWSSDK.Core",
    "version": "3.7.106.1",
    "totalDownloads": 432604023
  },
  {
    "id": "Microsoft.Extensions.Http",
    "version": "8.0.0-preview.2.23128.3",
    "totalDownloads": 421732613
  },
  {
    "id": "Newtonsoft.Json.Bson",
    "version": "1.0.3-beta1",
    "totalDownloads": 418190516
  },
  {
    "id": "Moq",
    "version": "4.18.4",
    "totalDownloads": 409073555
  },
  {
    "id": "System.Security.Cryptography.Pkcs",
    "version": "8.0.0-preview.2.23128.3",
    "totalDownloads": 398632521
  },
  {
    "id": "AutoMapper",
    "version": "12.0.1",
    "totalDownloads": 388610329
  },
  {
    "id": "Swashbuckle.AspNetCore.Swagger",
    "version": "6.5.0",
    "totalDownloads": 373938606
  },
  {
    "id": "Swashbuckle.AspNetCore.SwaggerGen",
    "version": "6.5.0",
    "totalDownloads": 372255025
  },
  {
    "id": "Microsoft.ApplicationInsights",
    "version": "2.22.0-beta2",
    "totalDownloads": 369226338
  },
  {
    "id": "System.Diagnostics.PerformanceCounter",
    "version": "8.0.0-preview.2.23128.3",
    "totalDownloads": 363436535
  },
  {
    "id": "Swashbuckle.AspNetCore.SwaggerUI",
    "version": "6.5.0",
    "totalDownloads": 329769214
  },
  {
    "id": "Polly",
    "version": "7.2.3",
    "totalDownloads": 324573183
  },
  {
    "id": "System.Runtime.Caching",
    "version": "8.0.0-preview.2.23128.3",
    "totalDownloads": 322870585
  },
  {
    "id": "Azure.Storage.Blobs",
    "version": "12.15.0",
    "totalDownloads": 110485166
  },
  {
    "id": "Serilog.Sinks.File",
    "version": "5.0.1-dev-00947",
    "totalDownloads": 317354217
  },
  {
    "id": "Microsoft.Extensions.Hosting",
    "version": "8.0.0-preview.2.23128.3",
    "totalDownloads": 306091478
  },
  {
    "id": "Microsoft.IdentityModel.Clients.ActiveDirectory",
    "version": "5.3.0",
    "totalDownloads": 305235487
  },
  {
    "id": "Swashbuckle.AspNetCore",
    "version": "6.5.0",
    "totalDownloads": 300831154
  },
  {
    "id": "xunit",
    "version": "2.4.2",
    "totalDownloads": 298957006
  },
  {
    "id": "Microsoft.Data.SqlClient",
    "version": "5.1.0",
    "totalDownloads": 295778468
  },
  {
    "id": "System.Threading.Channels",
    "version": "8.0.0-preview.2.23128.3",
    "totalDownloads": 292199089
  },
  {
    "id": "System.Diagnostics.EventLog",
    "version": "8.0.0-preview.2.23128.3",
    "totalDownloads": 282358909
  },
  {
    "id": "Microsoft.OpenApi",
    "version": "1.6.3",
    "totalDownloads": 282222959
  },
  {
    "id": "Serilog.Sinks.Console",
    "version": "4.1.1-dev-00910",
    "totalDownloads": 277978229
  },
  {
    "id": "Serilog.Extensions.Logging",
    "version": "3.1.1-dev-10338",
    "totalDownloads": 271190580
  },
  {
    "id": "Microsoft.Extensions.ApiDescription.Server",
    "version": "8.0.0-preview.2.23153.2",
    "totalDownloads": 251237503
  },
  {
    "id": "runtime.win-x86.runtime.native.System.Data.SqlClient.sni",
    "version": "4.4.0",
    "totalDownloads": 249893796
  },
  {
    "id": "runtime.win-x64.runtime.native.System.Data.SqlClient.sni",
    "version": "4.4.0",
    "totalDownloads": 249813519
  },
  {
    "id": "runtime.win-arm64.runtime.native.System.Data.SqlClient.sni",
    "version": "4.4.0",
    "totalDownloads": 249708494
  },
  {
    "id": "FluentValidation",
    "version": "11.5.1",
    "totalDownloads": 241549739
  },
  {
    "id": "Microsoft.AspNetCore.Mvc.NewtonsoftJson",
    "version": "8.0.0-preview.2.23153.2",
    "totalDownloads": 239328128
  },
  {
    "id": "NUnit",
    "version": "3.13.3",
    "totalDownloads": 238037989
  },
  {
    "id": "StackExchange.Redis",
    "version": "2.6.96",
    "totalDownloads": 236234248
  },
  {
    "id": "Serilog.Formatting.Compact",
    "version": "1.1.1-dev-00944",
    "totalDownloads": 235536265
  },
  {
    "id": "Serilog.Settings.Configuration",
    "version": "4.0.0-dev-00473",
    "totalDownloads": 226753741
  },
  {
    "id": "FluentAssertions",
    "version": "6.10.0",
    "totalDownloads": 225004826
  },
  {
    "id": "Azure.Security.KeyVault.Secrets",
    "version": "4.5.0",
    "totalDownloads": 95159607
  },
  {
    "id": "Google.Protobuf",
    "version": "3.22.1",
    "totalDownloads": 213474078
  },
  {
    "id": "NLog",
    "version": "5.1.2",
    "totalDownloads": 212260594
  },
  {
    "id": "Dapper",
    "version": "2.0.123",
    "totalDownloads": 210929151
  },
  {
    "id": "Microsoft.Extensions.Logging.EventLog",
    "version": "8.0.0-preview.2.23128.3",
    "totalDownloads": 209874685
  },
  {
    "id": "coverlet.collector",
    "version": "3.2.0",
    "totalDownloads": 205088873
  },
  {
    "id": "EntityFramework",
    "version": "6.4.4",
    "totalDownloads": 203133646
  },
  {
    "id": "Autofac",
    "version": "7.0.0",
    "totalDownloads": 202036394
  },
  {
    "id": "Pipelines.Sockets.Unofficial",
    "version": "2.2.2",
    "totalDownloads": 201413014
  },
  {
    "id": "Microsoft.Extensions.Diagnostics.HealthChecks.Abstractions",
    "version": "8.0.0-preview.2.23153.2",
    "totalDownloads": 201380892
  },
  {
    "id": "IdentityModel",
    "version": "6.1.0-preview.5",
    "totalDownloads": 196994611
  },
  {
    "id": "Microsoft.Azure.WebJobs",
    "version": "3.0.36",
    "totalDownloads": 195790246
  },
  {
    "id": "Microsoft.Extensions.Diagnostics.HealthChecks",
    "version": "8.0.0-preview.2.23153.2",
    "totalDownloads": 194189158
  },
  {
    "id": "RestSharp",
    "version": "109.0.1",
    "totalDownloads": 193565666
  },
  {
    "id": "Azure.Storage.Queues",
    "version": "12.13.0",
    "totalDownloads": 29170167
  },
  {
    "id": "Npgsql",
    "version": "8.0.0-preview.1",
    "totalDownloads": 192548979
  },
  {
    "id": "Humanizer.Core",
    "version": "2.14.1",
    "totalDownloads": 191946508
  },
  {
    "id": "Serilog.AspNetCore",
    "version": "6.1.1-dev-00295",
    "totalDownloads": 188792894
  },
  {
    "id": "Serilog.Extensions.Hosting",
    "version": "5.0.1",
    "totalDownloads": 181315742
  },
  {
    "id": "Portable.BouncyCastle",
    "version": "1.9.0",
    "totalDownloads": 176923039
  },
  {
    "id": "Microsoft.Data.SqlClient.SNI.runtime",
    "version": "5.1.0",
    "totalDownloads": 175915502
  },
  {
    "id": "System.CodeDom",
    "version": "8.0.0-preview.2.23128.3",
    "totalDownloads": 175816624
  },
  {
    "id": "Azure.Identity",
    "version": "1.9.0-beta.2",
    "totalDownloads": 172533635
  },
  {
    "id": "Microsoft.AspNet.Mvc",
    "version": "5.2.9",
    "totalDownloads": 170593592
  },
  {
    "id": "Serilog.Sinks.Debug",
    "version": "2.0.0",
    "totalDownloads": 168880673
  },
  {
    "id": "NUnit3TestAdapter",
    "version": "4.5.0-alpha.3",
    "totalDownloads": 168732770
  },
  {
    "id": "Microsoft.Azure.Amqp",
    "version": "2.6.1",
    "totalDownloads": 166620600
  },
  {
    "id": "Microsoft.Bcl.HashCode",
    "version": "1.1.1",
    "totalDownloads": 166180033
  },
  {
    "id": "Microsoft.AspNetCore.Mvc",
    "version": "2.2.0",
    "totalDownloads": 164071340
  },
  {
    "id": "log4net",
    "version": "2.0.15",
    "totalDownloads": 161617596
  },
  {
    "id": "Azure.Security.KeyVault.Certificates",
    "version": "4.5.0",
    "totalDownloads": 32910995
  },
  {
    "id": "Azure.Messaging.ServiceBus",
    "version": "7.13.1",
    "totalDownloads": 44477861
  },
  {
    "id": "Microsoft.Identity.Client.Extensions.Msal",
    "version": "2.27.0",
    "totalDownloads": 156936396
  },
  {
    "id": "Serilog.Sinks.PeriodicBatching",
    "version": "3.1.1-dev-00801",
    "totalDownloads": 153374940
  },
  {
    "id": "System.Memory.Data",
    "version": "8.0.0-preview.2.23128.3",
    "totalDownloads": 153131190
  },
  {
    "id": "jQuery",
    "version": "3.6.4",
    "totalDownloads": 150673281
  },
  {
    "id": "AutoMapper.Extensions.Microsoft.DependencyInjection",
    "version": "12.0.0",
    "totalDownloads": 148502205
  },
  {
    "id": "RabbitMQ.Client",
    "version": "6.4.0",
    "totalDownloads": 147189746
  },
  {
    "id": "AWSSDK.S3",
    "version": "3.7.103.31",
    "totalDownloads": 145972990
  },
  {
    "id": "MongoDB.Bson",
    "version": "2.19.0",
    "totalDownloads": 145295778
  },
  {
    "id": "Grpc.Core.Api",
    "version": "2.52.0",
    "totalDownloads": 142268131
  },
  {
    "id": "Microsoft.Extensions.Logging.ApplicationInsights",
    "version": "2.22.0-beta2",
    "totalDownloads": 139889802
  },
  {
    "id": "SQLitePCLRaw.core",
    "version": "2.1.4",
    "totalDownloads": 137873526
  },
  {
    "id": "Azure.Security.KeyVault.Keys",
    "version": "4.5.0",
    "totalDownloads": 12233891
  },
  {
    "id": "CsvHelper",
    "version": "30.0.1",
    "totalDownloads": 136152945
  },
  {
    "id": "JetBrains.Annotations",
    "version": "2023.2.0-eap1",
    "totalDownloads": 135068267
  },
  {
    "id": "MongoDB.Driver.Core",
    "version": "2.19.0",
    "totalDownloads": 135039049
  },
  {
    "id": "System.Interactive.Async",
    "version": "6.0.1",
    "totalDownloads": 134582499
  },
  {
    "id": "Microsoft.AspNet.WebApi",
    "version": "5.2.9",
    "totalDownloads": 132556544
  },
  {
    "id": "Elasticsearch.Net",
    "version": "7.17.5",
    "totalDownloads": 131598195
  },
  {
    "id": "Microsoft.Data.OData",
    "version": "5.8.5",
    "totalDownloads": 130913755
  }
]
