[
  {
    "id": "Newtonsoft.Json",
    "version": "13.0.1",
    "totalDownloads": 975230244
  },
  {
    "id": "Microsoft.Extensions.Logging",
    "version": "6.0.0-preview.3.21201.4",
    "totalDownloads": 535114888
  },
  {
    "id": "Microsoft.Extensions.DependencyInjection",
    "version": "6.0.0-preview.3.21201.4",
    "totalDownloads": 534795188
  },
  {
    "id": "Serilog",
    "version": "2.10.1-dev-01285",
    "totalDownloads": 224003412
  },
  {
    "id": "Castle.Core",
    "version": "4.4.1",
    "totalDownloads": 213093993
  },
  {
    "id": "Microsoft.EntityFrameworkCore",
    "version": "6.0.0-preview.3.21201.2",
    "totalDownloads": 207544070
  },
  {
    "id": "Moq",
    "version": "4.16.1",
    "totalDownloads": 179075621
  },
  {
    "id": "Microsoft.Bcl.AsyncInterfaces",
    "version": "6.0.0-preview.3.21201.4",
    "totalDownloads": 146537550
  },
  {
    "id": "AutoMapper",
    "version": "10.1.1",
    "totalDownloads": 144410064
  },
  {
    "id": "Microsoft.ApplicationInsights",
    "version": "2.17.0",
    "totalDownloads": 141116469
  },
  {
    "id": "AWSSDK.Core",
    "version": "3.7.0.13",
    "totalDownloads": 131409809
  },
  {
    "id": "xunit",
    "version": "2.4.1",
    "totalDownloads": 131261341
  },
  {
    "id": "Microsoft.IdentityModel.Clients.ActiveDirectory",
    "version": "5.2.9",
    "totalDownloads": 128496232
  },
  {
    "id": "EntityFramework",
    "version": "6.4.4",
    "totalDownloads": 121048922
  },
  {
    "id": "NUnit",
    "version": "3.13.1",
    "totalDownloads": 113371742
  },
  {
    "id": "System.Drawing.Common",
    "version": "6.0.0-preview.3.21201.4",
    "totalDownloads": 113092886
  },
  {
    "id": "Azure.Storage.Blobs",
    "version": "12.9.0-beta.3",
    "totalDownloads": 12609540
  },
  {
    "id": "Swashbuckle.AspNetCore.Swagger",
    "version": "6.1.2",
    "totalDownloads": 110593544
  },
  {
    "id": "Swashbuckle.AspNetCore.SwaggerGen",
    "version": "6.1.2",
    "totalDownloads": 109817004
  },
  {
    "id": "Microsoft.AspNet.Mvc",
    "version": "5.2.7",
    "totalDownloads": 108133608
  },
  {
    "id": "System.Text.Json",
    "version": "6.0.0-preview.3.21201.4",
    "totalDownloads": 106310168
  },
  {
    "id": "jQuery",
    "version": "3.6.0",
    "totalDownloads": 103887594
  },
  {
    "id": "Swashbuckle.AspNetCore.SwaggerUI",
    "version": "6.1.2",
    "totalDownloads": 103050386
  },
  {
    "id": "Microsoft.Win32.SystemEvents",
    "version": "6.0.0-preview.3.21201.4",
    "totalDownloads": 100741106
  },
  {
    "id": "Newtonsoft.Json.Bson",
    "version": "1.0.2",
    "totalDownloads": 97785437
  },
  {
    "id": "Swashbuckle.AspNetCore",
    "version": "6.1.2",
    "totalDownloads": 94087272
  },
  {
    "id": "Serilog.Sinks.File",
    "version": "5.0.0-dev-00909",
    "totalDownloads": 91441208
  },
  {
    "id": "Polly",
    "version": "7.2.2",
    "totalDownloads": 91382581
  },
  {
    "id": "NLog",
    "version": "4.7.9",
    "totalDownloads": 91140417
  },
  {
    "id": "Microsoft.Extensions.Http",
    "version": "6.0.0-preview.3.21201.4",
    "totalDownloads": 87865237
  },
  {
    "id": "Microsoft.AspNetCore.Mvc",
    "version": "2.2.0",
    "totalDownloads": 87498861
  },
  {
    "id": "FluentAssertions",
    "version": "6.0.0-alpha0002",
    "totalDownloads": 87257300
  },
  {
    "id": "Autofac",
    "version": "6.1.0",
    "totalDownloads": 86952422
  },
  {
    "id": "Microsoft.AspNet.WebApi",
    "version": "5.2.7",
    "totalDownloads": 85416759
  },
  {
    "id": "System.Diagnostics.PerformanceCounter",
    "version": "6.0.0-preview.3.21201.4",
    "totalDownloads": 84346166
  },
  {
    "id": "Microsoft.Data.OData",
    "version": "5.8.4",
    "totalDownloads": 83836378
  },
  {
    "id": "Azure.Storage.Queues",
    "version": "12.7.0-beta.3",
    "totalDownloads": 2783082
  },
  {
    "id": "Serilog.Extensions.Logging",
    "version": "3.0.2-dev-10284",
    "totalDownloads": 83078945
  },
  {
    "id": "Microsoft.Extensions.Hosting",
    "version": "6.0.0-preview.3.21201.4",
    "totalDownloads": 79210162
  },
  {
    "id": "Serilog.Sinks.Console",
    "version": "4.0.0-dev-00839",
    "totalDownloads": 78975298
  },
  {
    "id": "Dapper",
    "version": "2.0.78",
    "totalDownloads": 77782394
  },
  {
    "id": "log4net",
    "version": "2.0.12",
    "totalDownloads": 76555930
  },
  {
    "id": "RestSharp",
    "version": "106.11.8-alpha.0.12",
    "totalDownloads": 74494539
  },
  {
    "id": "WebGrease",
    "version": "1.6.0",
    "totalDownloads": 73305246
  },
  {
    "id": "FluentValidation",
    "version": "10.0.3",
    "totalDownloads": 72838750
  },
  {
    "id": "System.Security.Cryptography.Pkcs",
    "version": "6.0.0-preview.3.21201.4",
    "totalDownloads": 72635722
  },
  {
    "id": "Microsoft.Identity.Client",
    "version": "4.29.0",
    "totalDownloads": 71481033
  },
  {
    "id": "StackExchange.Redis",
    "version": "2.2.4",
    "totalDownloads": 70217242
  },
  {
    "id": "IdentityModel",
    "version": "5.1.0",
    "totalDownloads": 69433120
  },
  {
    "id": "Microsoft.Azure.WebJobs",
    "version": "3.0.27",
    "totalDownloads": 68002670
  },
  {
    "id": "Azure.Security.KeyVault.Secrets",
    "version": "4.2.0-beta.4",
    "totalDownloads": 8010659
  },
  {
    "id": "System.Runtime.Caching",
    "version": "6.0.0-preview.3.21201.4",
    "totalDownloads": 66805156
  },
  {
    "id": "NUnit3TestAdapter",
    "version": "4.0.0-beta.2",
    "totalDownloads": 65148793
  },
  {
    "id": "Antlr",
    "version": "3.5.0.2",
    "totalDownloads": 64176737
  },
  {
    "id": "System.Windows.Extensions",
    "version": "6.0.0-preview.3.21201.4",
    "totalDownloads": 62386491
  },
  {
    "id": "System.Interactive.Async",
    "version": "5.0.0",
    "totalDownloads": 61029894
  },
  {
    "id": "Azure.Security.KeyVault.Certificates",
    "version": "4.2.0-beta.5",
    "totalDownloads": 1978100
  },
  {
    "id": "Microsoft.Azure.Services.AppAuthentication",
    "version": "1.6.1",
    "totalDownloads": 60896700
  },
  {
    "id": "Serilog.Formatting.Compact",
    "version": "1.1.1-dev-00940",
    "totalDownloads": 60278207
  },
  {
    "id": "Azure.Security.KeyVault.Keys",
    "version": "4.2.0-beta.5",
    "totalDownloads": 1110075
  },
  {
    "id": "Serilog.Settings.Configuration",
    "version": "3.2.0-dev-00266",
    "totalDownloads": 60034132
  },
  {
    "id": "System.Threading.Channels",
    "version": "6.0.0-preview.3.21201.4",
    "totalDownloads": 59507897
  },
  {
    "id": "Microsoft.OpenApi",
    "version": "1.2.3",
    "totalDownloads": 58461101
  },
  {
    "id": "Npgsql",
    "version": "6.0.0-preview3",
    "totalDownloads": 58013334
  },
  {
    "id": "runtime.win-arm64.runtime.native.System.Data.SqlClient.sni",
    "version": "4.4.0",
    "totalDownloads": 55498131
  },
  {
    "id": "runtime.win-x64.runtime.native.System.Data.SqlClient.sni",
    "version": "4.4.0",
    "totalDownloads": 55459789
  },
  {
    "id": "runtime.win-x86.runtime.native.System.Data.SqlClient.sni",
    "version": "4.4.0",
    "totalDownloads": 55450983
  },
  {
    "id": "Google.Protobuf",
    "version": "3.16.0-rc1",
    "totalDownloads": 55384905
  },
  {
    "id": "Microsoft.AspNetCore.Mvc.NewtonsoftJson",
    "version": "6.0.0-preview.3.21201.13",
    "totalDownloads": 55304260
  },
  {
    "id": "Modernizr",
    "version": "2.8.3",
    "totalDownloads": 54693860
  },
  {
    "id": "Microsoft.Data.SqlClient",
    "version": "3.0.0-preview2.21106.5",
    "totalDownloads": 53844746
  },
  {
    "id": "Serilog.AspNetCore",
    "version": "4.1.0",
    "totalDownloads": 53727438
  },
  {
    "id": "jQuery.Validation",
    "version": "1.19.3",
    "totalDownloads": 53648433
  },
  {
    "id": "System.Diagnostics.EventLog",
    "version": "6.0.0-preview.3.21201.4",
    "totalDownloads": 52760680
  },
  {
    "id": "bootstrap",
    "version": "5.0.0-beta3",
    "totalDownloads": 52170716
  },
  {
    "id": "Remotion.Linq",
    "version": "2.2.0",
    "totalDownloads": 51592666
  },
  {
    "id": "Microsoft.Extensions.ApiDescription.Server",
    "version": "6.0.0-preview.3.21201.13",
    "totalDownloads": 51265471
  },
  {
    "id": "RabbitMQ.Client",
    "version": "6.2.1",
    "totalDownloads": 50208440
  },
  {
    "id": "Pipelines.Sockets.Unofficial",
    "version": "2.2.0",
    "totalDownloads": 50014969
  },
  {
    "id": "Microsoft.Azure.Amqp",
    "version": "2.4.13",
    "totalDownloads": 49869024
  },
  {
    "id": "Microsoft.Owin.Security.OAuth",
    "version": "4.1.1",
    "totalDownloads": 49800782
  },
  {
    "id": "Serilog.Sinks.PeriodicBatching",
    "version": "2.3.1-dev-00780",
    "totalDownloads": 49672179
  },
  {
    "id": "AWSSDK.S3",
    "version": "3.7.0.14",
    "totalDownloads": 49132255
  },
  {
    "id": "WebActivatorEx",
    "version": "2.2.0",
    "totalDownloads": 47501800
  },
  {
    "id": "Azure.Messaging.EventHubs",
    "version": "5.4.0",
    "totalDownloads": 1210404
  },
  {
    "id": "Microsoft.Bcl.HashCode",
    "version": "1.1.1",
    "totalDownloads": 46626378
  },
  {
    "id": "MongoDB.Bson",
    "version": "2.13.0-beta1",
    "totalDownloads": 45294573
  },
  {
    "id": "CsvHelper",
    "version": "26.1.0",
    "totalDownloads": 45026398
  },
  {
    "id": "AutoMapper.Extensions.Microsoft.DependencyInjection",
    "version": "8.1.1",
    "totalDownloads": 44883925
  },
  {
    "id": "Portable.BouncyCastle",
    "version": "1.8.10",
    "totalDownloads": 44212812
  },
  {
    "id": "SQLitePCLRaw.core",
    "version": "2.0.5-pre20210119130047",
    "totalDownloads": 44053515
  },
  {
    "id": "Elasticsearch.Net",
    "version": "7.12.0",
    "totalDownloads": 43824451
  },
  {
    "id": "HtmlAgilityPack",
    "version": "1.11.32",
    "totalDownloads": 43541953
  },
  {
    "id": "MongoDB.Driver.Core",
    "version": "2.13.0-beta1",
    "totalDownloads": 42547214
  },
  {
    "id": "MongoDB.Driver",
    "version": "2.13.0-beta1",
    "totalDownloads": 42071323
  },
  {
    "id": "Microsoft.Extensions.Logging.EventLog",
    "version": "6.0.0-preview.3.21201.4",
    "totalDownloads": 42000887
  },
  {
    "id": "Google.Apis.Core",
    "version": "1.51.0",
    "totalDownloads": 41074730
  },
  {
    "id": "CommonServiceLocator",
    "version": "2.0.6",
    "totalDownloads": 40833233
  },
  {
    "id": "StyleCop.Analyzers",
    "version": "1.2.0-beta.333",
    "totalDownloads": 40525740
  },
  {
    "id": "Google.Apis",
    "version": "1.51.0",
    "totalDownloads": 40373570
  }
]
