[
  {
    "id": "Newtonsoft.Json",
    "version": "13.0.5-beta1",
    "totalDownloads": 7429702655
  },
  {
    "id": "Microsoft.Extensions.DependencyInjection",
    "version": "10.0.1",
    "totalDownloads": 6051001758
  },
  {
    "id": "Microsoft.Extensions.Logging",
    "version": "10.0.1",
    "totalDownloads": 5756627944
  },
  {
    "id": "System.Text.Json",
    "version": "10.0.1",
    "totalDownloads": 4956292190
  },
  {
    "id": "Microsoft.Bcl.AsyncInterfaces",
    "version": "10.0.1",
    "totalDownloads": 3405125692
  },
  {
    "id": "Azure.Core",
    "version": "1.50.0",
    "totalDownloads": 2919905601
  },
  {
    "id": "System.Drawing.Common",
    "version": "10.0.1",
    "totalDownloads": 2355953869
  },
  {
    "id": "Serilog",
    "version": "4.3.1-dev-02395",
    "totalDownloads": 2302935700
  },
  {
    "id": "Microsoft.Win32.SystemEvents",
    "version": "10.0.1",
    "totalDownloads": 2177706622
  },
  {
    "id": "Microsoft.Identity.Client",
    "version": "4.81.0",
    "totalDownloads": 2039343332
  },
  {
    "id": "Microsoft.IdentityModel.Abstractions",
    "version": "8.15.0",
    "totalDownloads": 1998769674
  },
  {
    "id": "Microsoft.EntityFrameworkCore",
    "version": "10.0.1",
    "totalDownloads": 1881196954
  },
  {
    "id": "System.Windows.Extensions",
    "version": "10.0.1",
    "totalDownloads": 1832874046
  },
  {
    "id": "Microsoft.Extensions.Http",
    "version": "10.0.1",
    "totalDownloads": 1811192933
  },
  {
    "id": "System.Diagnostics.EventLog",
    "version": "10.0.1",
    "totalDownloads": 1690718921
  },
  {
    "id": "System.Security.Cryptography.Pkcs",
    "version": "10.0.1",
    "totalDownloads": 1592667350
  },
  {
    "id": "AWSSDK.Core",
    "version": "4.0.3.8",
    "totalDownloads": 1525948763
  },
  {
    "id": "Castle.Core",
    "version": "5.2.1",
    "totalDownloads": 1366734676
  },
  {
    "id": "Azure.Identity",
    "version": "1.18.0-beta.2",
    "totalDownloads": 1339709377
  },
  {
    "id": "System.Threading.Channels",
    "version": "10.0.1",
    "totalDownloads": 1231801784
  },
  {
    "id": "Microsoft.Identity.Client.Extensions.Msal",
    "version": "4.81.0",
    "totalDownloads": 1205292891
  },
  {
    "id": "System.Memory.Data",
    "version": "10.0.1",
    "totalDownloads": 1195163846
  },
  {
    "id": "Swashbuckle.AspNetCore.SwaggerGen",
    "version": "10.1.0",
    "totalDownloads": 1184966398
  },
  {
    "id": "Polly",
    "version": "8.6.5",
    "totalDownloads": 1183619092
  },
  {
    "id": "Swashbuckle.AspNetCore.Swagger",
    "version": "10.1.0",
    "totalDownloads": 1179047144
  },
  {
    "id": "Microsoft.OpenApi",
    "version": "3.1.2",
    "totalDownloads": 1169077081
  },
  {
    "id": "Microsoft.Data.SqlClient",
    "version": "7.0.0-preview3.25342.7",
    "totalDownloads": 1152118177
  },
  {
    "id": "Newtonsoft.Json.Bson",
    "version": "1.0.3",
    "totalDownloads": 1144744291
  },
  {
    "id": "System.Formats.Asn1",
    "version": "10.0.1",
    "totalDownloads": 1144592344
  },
  {
    "id": "System.Runtime.Caching",
    "version": "10.0.1",
    "totalDownloads": 1143969172
  },
  {
    "id": "Microsoft.Extensions.Hosting",
    "version": "10.0.1",
    "totalDownloads": 1118957805
  },
  {
    "id": "System.Diagnostics.PerformanceCounter",
    "version": "10.0.1",
    "totalDownloads": 1026524098
  },
  {
    "id": "Google.Protobuf",
    "version": "3.33.2",
    "totalDownloads": 1006110560
  },
  {
    "id": "Swashbuckle.AspNetCore.SwaggerUI",
    "version": "10.1.0",
    "totalDownloads": 1005408479
  },
  {
    "id": "Microsoft.ApplicationInsights",
    "version": "3.0.0-beta1",
    "totalDownloads": 997389641
  },
  {
    "id": "System.CodeDom",
    "version": "10.0.1",
    "totalDownloads": 992666000
  },
  {
    "id": "Moq",
    "version": "4.20.72",
    "totalDownloads": 980282838
  },
  {
    "id": "AutoMapper",
    "version": "16.0.0",
    "totalDownloads": 971698438
  },
  {
    "id": "Swashbuckle.AspNetCore",
    "version": "10.1.0",
    "totalDownloads": 933404012
  },
  {
    "id": "Serilog.Sinks.File",
    "version": "8.0.0-dev-02318",
    "totalDownloads": 923516582
  },
  {
    "id": "Azure.Storage.Blobs",
    "version": "12.27.0",
    "totalDownloads": 543091844
  },
  {
    "id": "Serilog.Sinks.Console",
    "version": "6.1.1",
    "totalDownloads": 901111651
  },
  {
    "id": "Microsoft.Extensions.ApiDescription.Server",
    "version": "10.0.1",
    "totalDownloads": 899222821
  },
  {
    "id": "Microsoft.Data.SqlClient.SNI.runtime",
    "version": "6.0.2",
    "totalDownloads": 884275133
  },
  {
    "id": "Microsoft.Extensions.Logging.EventLog",
    "version": "10.0.1",
    "totalDownloads": 873669503
  },
  {
    "id": "Microsoft.Extensions.Diagnostics.Abstractions",
    "version": "10.0.1",
    "totalDownloads": 861244152
  },
  {
    "id": "Serilog.Extensions.Logging",
    "version": "10.0.0",
    "totalDownloads": 838957784
  },
  {
    "id": "StackExchange.Redis",
    "version": "2.10.1",
    "totalDownloads": 837070100
  },
  {
    "id": "Microsoft.Extensions.Diagnostics.HealthChecks.Abstractions",
    "version": "10.0.1",
    "totalDownloads": 835759734
  },
  {
    "id": "Grpc.Core.Api",
    "version": "2.76.0",
    "totalDownloads": 828773608
  },
  {
    "id": "Microsoft.Extensions.Diagnostics.HealthChecks",
    "version": "10.0.1",
    "totalDownloads": 810010518
  },
  {
    "id": "Microsoft.NET.Sdk.Aspire.Manifest-8.0.100",
    "version": "8.2.2",
    "totalDownloads": 802755413
  },
  {
    "id": "xunit",
    "version": "2.9.3",
    "totalDownloads": 800350763
  },
  {
    "id": "FluentValidation",
    "version": "12.1.1",
    "totalDownloads": 798698486
  },
  {
    "id": "Humanizer.Core",
    "version": "3.0.1",
    "totalDownloads": 772387600
  },
  {
    "id": "coverlet.collector",
    "version": "6.0.4",
    "totalDownloads": 758715111
  },
  {
    "id": "Serilog.Settings.Configuration",
    "version": "10.0.0",
    "totalDownloads": 741246319
  },
  {
    "id": "Serilog.Formatting.Compact",
    "version": "3.0.0",
    "totalDownloads": 736375880
  },
  {
    "id": "Azure.Security.KeyVault.Secrets",
    "version": "4.8.0",
    "totalDownloads": 497460335
  },
  {
    "id": "Pipelines.Sockets.Unofficial",
    "version": "2.2.8",
    "totalDownloads": 690510251
  },
  {
    "id": "Microsoft.AspNetCore.Mvc.NewtonsoftJson",
    "version": "10.0.1",
    "totalDownloads": 673481172
  },
  {
    "id": "Npgsql",
    "version": "10.0.1",
    "totalDownloads": 673115974
  },
  {
    "id": "runtime.win-x86.runtime.native.System.Data.SqlClient.sni",
    "version": "4.4.0",
    "totalDownloads": 637346830
  },
  {
    "id": "runtime.win-x64.runtime.native.System.Data.SqlClient.sni",
    "version": "4.4.0",
    "totalDownloads": 637307652
  },
  {
    "id": "runtime.win-arm64.runtime.native.System.Data.SqlClient.sni",
    "version": "4.4.0",
    "totalDownloads": 637105389
  },
  {
    "id": "Serilog.Extensions.Hosting",
    "version": "10.0.0",
    "totalDownloads": 635287238
  },
  {
    "id": "FluentAssertions",
    "version": "8.8.0",
    "totalDownloads": 610465764
  },
  {
    "id": "Grpc.Net.Common",
    "version": "2.76.0",
    "totalDownloads": 605524887
  },
  {
    "id": "Serilog.AspNetCore",
    "version": "10.0.0",
    "totalDownloads": 603168916
  },
  {
    "id": "Microsoft.NET.Workload.Mono.ToolChain.Current.Manifest-8.0.100",
    "version": "8.0.22",
    "totalDownloads": 600132847
  },
  {
    "id": "Microsoft.NET.Workload.Emscripten.Current.Manifest-8.0.100",
    "version": "8.0.22",
    "totalDownloads": 599899153
  },
  {
    "id": "Microsoft.NET.Workload.Emscripten.net7.Manifest-8.0.100",
    "version": "8.0.22",
    "totalDownloads": 599616081
  },
  {
    "id": "Microsoft.NET.Workload.Mono.ToolChain.net7.Manifest-8.0.100",
    "version": "8.0.22",
    "totalDownloads": 599204917
  },
  {
    "id": "Microsoft.NET.Workload.Emscripten.net6.Manifest-8.0.100",
    "version": "8.0.22",
    "totalDownloads": 598772718
  },
  {
    "id": "Microsoft.NET.Workload.Mono.ToolChain.net6.Manifest-8.0.100",
    "version": "8.0.22",
    "totalDownloads": 598302039
  },
  {
    "id": "Azure.Storage.Common",
    "version": "12.26.0",
    "totalDownloads": 595612817
  },
  {
    "id": "Dapper",
    "version": "2.1.66",
    "totalDownloads": 590746424
  },
  {
    "id": "Grpc.Net.Client",
    "version": "2.76.0",
    "totalDownloads": 582869531
  },
  {
    "id": "System.ClientModel",
    "version": "1.8.1",
    "totalDownloads": 579809846
  },
  {
    "id": "Microsoft.Extensions.Diagnostics",
    "version": "10.0.1",
    "totalDownloads": 568330320
  },
  {
    "id": "Serilog.Sinks.Debug",
    "version": "3.0.0",
    "totalDownloads": 567381839
  },
  {
    "id": "Microsoft.NET.Sdk.iOS.Manifest-8.0.100",
    "version": "18.0.8319",
    "totalDownloads": 566241304
  },
  {
    "id": "Microsoft.NET.Sdk.Android.Manifest-8.0.100",
    "version": "34.0.154",
    "totalDownloads": 565177727
  },
  {
    "id": "Microsoft.NET.Sdk.MacCatalyst.Manifest-8.0.100",
    "version": "18.0.8319",
    "totalDownloads": 565081640
  },
  {
    "id": "Microsoft.NET.Sdk.macOS.Manifest-8.0.100",
    "version": "15.0.8319",
    "totalDownloads": 565059986
  },
  {
    "id": "Microsoft.NET.Sdk.tvOS.Manifest-8.0.100",
    "version": "18.0.8319",
    "totalDownloads": 564745684
  },
  {
    "id": "Microsoft.NET.Sdk.Maui.Manifest-8.0.100",
    "version": "8.0.100",
    "totalDownloads": 564539869
  },
  {
    "id": "NUnit",
    "version": "4.4.0",
    "totalDownloads": 563263400
  },
  {
    "id": "Microsoft.IdentityModel.Clients.ActiveDirectory",
    "version": "5.3.0",
    "totalDownloads": 541932625
  },
  {
    "id": "Microsoft.Azure.Amqp",
    "version": "2.7.0",
    "totalDownloads": 524857533
  },
  {
    "id": "NLog",
    "version": "6.0.7",
    "totalDownloads": 501076742
  },
  {
    "id": "Microsoft.Azure.WebJobs",
    "version": "3.0.44",
    "totalDownloads": 495737463
  },
  {
    "id": "OpenTelemetry.Api",
    "version": "1.14.0",
    "totalDownloads": 489636158
  },
  {
    "id": "AWSSDK.S3",
    "version": "4.0.16.4",
    "totalDownloads": 485674188
  },
  {
    "id": "RestSharp",
    "version": "113.0.1-alpha.0.3",
    "totalDownloads": 483794133
  },
  {
    "id": "Azure.Messaging.ServiceBus",
    "version": "7.20.1",
    "totalDownloads": 288420548
  },
  {
    "id": "Autofac",
    "version": "9.0.0",
    "totalDownloads": 465604744
  },
  {
    "id": "NUnit3TestAdapter",
    "version": "6.1.0",
    "totalDownloads": 444956768
  },
  {
    "id": "Azure.Storage.Queues",
    "version": "12.25.0",
    "totalDownloads": 155605917
  },
  {
    "id": "Portable.BouncyCastle",
    "version": "1.9.0",
    "totalDownloads": 443933981
  }
]
